[
  {
    "model": "meta-llama/Llama-3.2-1B",
    "model_short": "Llama-3.2-1B",
    "task": "ioi",
    "lambda_sparsity": 0.7,
    "seed": 42,
    "num_epochs": 500,
    "learning_rate": 0.01,
    "batch_size": 32,
    "training_time_seconds": 366.88086915016174,
    "baseline_accuracy": 1.0,
    "baseline_logit_diff": 5.87525025025025,
    "final_accuracy": 0.964964964964965,
    "final_logit_diff": 6.073573573573573,
    "final_kl_div": 0.8374860456159284,
    "final_exact_match": 0.5425425425425425,
    "accuracy_drop": 0.03503503503503502,
    "final_train_loss": 17.930901663643972,
    "final_train_kl": 0.3521598790373121,
    "final_train_sparsity": 25.352722440447128,
    "final_train_task_loss": 0.2611607142857143,
    "compression_ratio": 10.93515074282283,
    "reduction_percentage": 90.85517864802787,
    "active_prunable_params": 88986293,
    "total_prunable_params": 973078528,
    "effective_compression": 3.512201497026661,
    "pruned_pct_embedding": 100.0,
    "active_embedding": 0,
    "total_embedding": 1,
    "pruned_pct_layer_level": 0.0,
    "active_layer_level": 16,
    "total_layer_level": 16,
    "pruned_pct_attention_blocks": 62.5,
    "active_attention_blocks": 6,
    "total_attention_blocks": 16,
    "pruned_pct_mlp_blocks": 43.75,
    "active_mlp_blocks": 9,
    "total_mlp_blocks": 16,
    "pruned_pct_attention_heads": 91.6015625,
    "active_attention_heads": 43,
    "total_attention_heads": 512,
    "pruned_pct_attention_neurons": 93.1060791015625,
    "active_attention_neurons": 2259,
    "total_attention_neurons": 32768,
    "pruned_pct_mlp_hidden": 80.69686889648438,
    "active_mlp_hidden": 25301,
    "total_mlp_hidden": 131072,
    "pruned_pct_mlp_output": 81.744384765625,
    "active_mlp_output": 5982,
    "total_mlp_output": 32768,
    "sparsity_attention_blocks": 6.006345748901367,
    "sparsity_mlp_blocks": 9.003351211547852,
    "sparsity_attention_heads": 1.465510368347168,
    "sparsity_attention_neurons": 1.37998628616333,
    "sparsity_mlp_hidden": 4.0740885734558105,
    "sparsity_mlp_output": 3.407637357711792,
    "sparsity_total_sparsity": 25.3369197845459
  },
  {
    "model": "meta-llama/Llama-3.2-1B",
    "model_short": "Llama-3.2-1B",
    "task": "ioi",
    "lambda_sparsity": 0.73,
    "seed": 42,
    "num_epochs": 500,
    "learning_rate": 0.01,
    "batch_size": 32,
    "training_time_seconds": 369.0339994430542,
    "baseline_accuracy": 1.0,
    "baseline_logit_diff": 5.87525025025025,
    "final_accuracy": 0.9169169169169169,
    "final_logit_diff": 4.2825325325325325,
    "final_kl_div": 0.8939587781140516,
    "final_exact_match": 0.5265265265265265,
    "accuracy_drop": 0.0830830830830831,
    "final_train_loss": 17.5304320199149,
    "final_train_kl": 0.31534971935408457,
    "final_train_sparsity": 23.860605784824916,
    "final_train_task_loss": 0.10016741071428571,
    "compression_ratio": 11.195410919246816,
    "reduction_percentage": 91.06776868474896,
    "active_prunable_params": 86917625,
    "total_prunable_params": 973078528,
    "effective_compression": 3.5329691556467573,
    "pruned_pct_embedding": 100.0,
    "active_embedding": 0,
    "total_embedding": 1,
    "pruned_pct_layer_level": 0.0,
    "active_layer_level": 16,
    "total_layer_level": 16,
    "pruned_pct_attention_blocks": 68.75,
    "active_attention_blocks": 5,
    "total_attention_blocks": 16,
    "pruned_pct_mlp_blocks": 43.75,
    "active_mlp_blocks": 9,
    "total_mlp_blocks": 16,
    "pruned_pct_attention_heads": 92.3828125,
    "active_attention_heads": 39,
    "total_attention_heads": 512,
    "pruned_pct_attention_neurons": 93.61572265625,
    "active_attention_neurons": 2092,
    "total_attention_neurons": 32768,
    "pruned_pct_mlp_hidden": 81.2103271484375,
    "active_mlp_hidden": 24628,
    "total_mlp_hidden": 131072,
    "pruned_pct_mlp_output": 80.6396484375,
    "active_mlp_output": 6344,
    "total_mlp_output": 32768,
    "sparsity_attention_blocks": 5.018413543701172,
    "sparsity_mlp_blocks": 9.007062911987305,
    "sparsity_attention_heads": 1.3069348335266113,
    "sparsity_attention_neurons": 1.2817293405532837,
    "sparsity_mlp_hidden": 3.789426565170288,
    "sparsity_mlp_output": 3.4443817138671875,
    "sparsity_total_sparsity": 23.847946166992188
  },
  {
    "model": "meta-llama/Llama-3.2-1B",
    "model_short": "Llama-3.2-1B",
    "task": "ioi",
    "lambda_sparsity": 0.75,
    "seed": 42,
    "num_epochs": 500,
    "learning_rate": 0.01,
    "batch_size": 32,
    "training_time_seconds": 368.6332893371582,
    "baseline_accuracy": 1.0,
    "baseline_logit_diff": 5.87525025025025,
    "final_accuracy": 0.9039039039039038,
    "final_logit_diff": 3.933933933933934,
    "final_kl_div": 0.9091236011402027,
    "final_exact_match": 0.5195195195195195,
    "accuracy_drop": 0.09609609609609615,
    "final_train_loss": 17.58972958156041,
    "final_train_kl": 0.3304033577442169,
    "final_train_sparsity": 23.296428680419922,
    "final_train_task_loss": 0.13922991071428573,
    "compression_ratio": 11.957338871456914,
    "reduction_percentage": 91.63693518474184,
    "active_prunable_params": 81379188,
    "total_prunable_params": 973078528,
    "effective_compression": 3.589798760899018,
    "pruned_pct_embedding": 100.0,
    "active_embedding": 0,
    "total_embedding": 1,
    "pruned_pct_layer_level": 0.0,
    "active_layer_level": 16,
    "total_layer_level": 16,
    "pruned_pct_attention_blocks": 68.75,
    "active_attention_blocks": 5,
    "total_attention_blocks": 16,
    "pruned_pct_mlp_blocks": 43.75,
    "active_mlp_blocks": 9,
    "total_mlp_blocks": 16,
    "pruned_pct_attention_heads": 92.7734375,
    "active_attention_heads": 37,
    "total_attention_heads": 512,
    "pruned_pct_attention_neurons": 93.9178466796875,
    "active_attention_neurons": 1993,
    "total_attention_neurons": 32768,
    "pruned_pct_mlp_hidden": 82.293701171875,
    "active_mlp_hidden": 23208,
    "total_mlp_hidden": 131072,
    "pruned_pct_mlp_output": 81.5216064453125,
    "active_mlp_output": 6055,
    "total_mlp_output": 32768,
    "sparsity_attention_blocks": 5.017702579498291,
    "sparsity_mlp_blocks": 9.005411148071289,
    "sparsity_attention_heads": 1.259319543838501,
    "sparsity_attention_neurons": 1.2227931022644043,
    "sparsity_mlp_hidden": 3.511993885040283,
    "sparsity_mlp_output": 3.267521619796753,
    "sparsity_total_sparsity": 23.284740447998047
  },
  {
    "model": "meta-llama/Llama-3.2-1B",
    "model_short": "Llama-3.2-1B",
    "task": "ioi",
    "lambda_sparsity": 0.78,
    "seed": 42,
    "num_epochs": 500,
    "learning_rate": 0.01,
    "batch_size": 32,
    "training_time_seconds": 367.82401061058044,
    "baseline_accuracy": 1.0,
    "baseline_logit_diff": 5.87525025025025,
    "final_accuracy": 0.8798798798798799,
    "final_logit_diff": 3.491116116116116,
    "final_kl_div": 0.928076514014014,
    "final_exact_match": 0.48848848848848847,
    "accuracy_drop": 0.12012012012012008,
    "final_train_loss": 17.545307976858957,
    "final_train_kl": 0.3406482296330588,
    "final_train_sparsity": 22.33793749128069,
    "final_train_task_loss": 0.21261160714285715,
    "compression_ratio": 13.358121260070789,
    "reduction_percentage": 92.5139173351485,
    "active_prunable_params": 72845463,
    "total_prunable_params": 973078528,
    "effective_compression": 3.681032585032763,
    "pruned_pct_embedding": 100.0,
    "active_embedding": 0,
    "total_embedding": 1,
    "pruned_pct_layer_level": 0.0,
    "active_layer_level": 16,
    "total_layer_level": 16,
    "pruned_pct_attention_blocks": 68.75,
    "active_attention_blocks": 5,
    "total_attention_blocks": 16,
    "pruned_pct_mlp_blocks": 43.75,
    "active_mlp_blocks": 9,
    "total_mlp_blocks": 16,
    "pruned_pct_attention_heads": 92.96875,
    "active_attention_heads": 36,
    "total_attention_heads": 512,
    "pruned_pct_attention_neurons": 94.15283203125,
    "active_attention_neurons": 1916,
    "total_attention_neurons": 32768,
    "pruned_pct_mlp_hidden": 84.26742553710938,
    "active_mlp_hidden": 20621,
    "total_mlp_hidden": 131072,
    "pruned_pct_mlp_output": 82.8277587890625,
    "active_mlp_output": 5627,
    "total_mlp_output": 32768,
    "sparsity_attention_blocks": 5.014227867126465,
    "sparsity_mlp_blocks": 9.002098083496094,
    "sparsity_attention_heads": 1.1929333209991455,
    "sparsity_attention_neurons": 1.1083600521087646,
    "sparsity_mlp_hidden": 3.0421249866485596,
    "sparsity_mlp_output": 2.9702017307281494,
    "sparsity_total_sparsity": 22.329944610595703
  },
  {
    "model": "meta-llama/Llama-3.2-1B",
    "model_short": "Llama-3.2-1B",
    "task": "ioi",
    "lambda_sparsity": 0.8,
    "seed": 42,
    "num_epochs": 500,
    "learning_rate": 0.01,
    "batch_size": 32,
    "training_time_seconds": 366.0016052722931,
    "baseline_accuracy": 1.0,
    "baseline_logit_diff": 5.87525025025025,
    "final_accuracy": 0.8408408408408409,
    "final_logit_diff": 3.0521771771771773,
    "final_kl_div": 0.9532272751266891,
    "final_exact_match": 0.47347347347347346,
    "accuracy_drop": 0.15915915915915912,
    "final_train_loss": 17.50126620701381,
    "final_train_kl": 0.36605964388166157,
    "final_train_sparsity": 21.713708060128347,
    "final_train_task_loss": 0.28543526785714285,
    "compression_ratio": 14.44915409257377,
    "reduction_percentage": 93.079179628142,
    "active_prunable_params": 67345017,
    "total_prunable_params": 973078528,
    "effective_compression": 3.7423364516080557,
    "pruned_pct_embedding": 100.0,
    "active_embedding": 0,
    "total_embedding": 1,
    "pruned_pct_layer_level": 0.0,
    "active_layer_level": 16,
    "total_layer_level": 16,
    "pruned_pct_attention_blocks": 68.75,
    "active_attention_blocks": 5,
    "total_attention_blocks": 16,
    "pruned_pct_mlp_blocks": 43.75,
    "active_mlp_blocks": 9,
    "total_mlp_blocks": 16,
    "pruned_pct_attention_heads": 93.359375,
    "active_attention_heads": 34,
    "total_attention_heads": 512,
    "pruned_pct_attention_neurons": 94.3634033203125,
    "active_attention_neurons": 1847,
    "total_attention_neurons": 32768,
    "pruned_pct_mlp_hidden": 85.44921875,
    "active_mlp_hidden": 19072,
    "total_mlp_hidden": 131072,
    "pruned_pct_mlp_output": 83.831787109375,
    "active_mlp_output": 5298,
    "total_mlp_output": 32768,
    "sparsity_attention_blocks": 5.010667324066162,
    "sparsity_mlp_blocks": 9.002009391784668,
    "sparsity_attention_heads": 1.1221065521240234,
    "sparsity_attention_neurons": 1.0403389930725098,
    "sparsity_mlp_hidden": 2.7667441368103027,
    "sparsity_mlp_output": 2.7652475833892822,
    "sparsity_total_sparsity": 21.707111358642578
  },
  {
    "model": "meta-llama/Llama-3.2-1B",
    "model_short": "Llama-3.2-1B",
    "task": "ioi",
    "lambda_sparsity": 0.83,
    "seed": 42,
    "num_epochs": 500,
    "learning_rate": 0.01,
    "batch_size": 32,
    "training_time_seconds": 365.38216400146484,
    "baseline_accuracy": 1.0,
    "baseline_logit_diff": 5.87525025025025,
    "final_accuracy": 0.8108108108108109,
    "final_logit_diff": 2.674299299299299,
    "final_kl_div": 0.9878862016313188,
    "final_exact_match": 0.44844844844844844,
    "accuracy_drop": 0.18918918918918914,
    "final_train_loss": 17.627456665039062,
    "final_train_kl": 0.39039161801338196,
    "final_train_sparsity": 21.047358649117605,
    "final_train_task_loss": 0.5398995535714286,
    "compression_ratio": 15.820189973280181,
    "reduction_percentage": 93.67896338988994,
    "active_prunable_params": 61508650,
    "total_prunable_params": 973078528,
    "effective_compression": 3.8096571773945413,
    "pruned_pct_embedding": 100.0,
    "active_embedding": 0,
    "total_embedding": 1,
    "pruned_pct_layer_level": 0.0,
    "active_layer_level": 16,
    "total_layer_level": 16,
    "pruned_pct_attention_blocks": 68.75,
    "active_attention_blocks": 5,
    "total_attention_blocks": 16,
    "pruned_pct_mlp_blocks": 43.75,
    "active_mlp_blocks": 9,
    "total_mlp_blocks": 16,
    "pruned_pct_attention_heads": 93.359375,
    "active_attention_heads": 34,
    "total_attention_heads": 512,
    "pruned_pct_attention_neurons": 94.451904296875,
    "active_attention_neurons": 1818,
    "total_attention_neurons": 32768,
    "pruned_pct_mlp_hidden": 86.87591552734375,
    "active_mlp_hidden": 17202,
    "total_mlp_hidden": 131072,
    "pruned_pct_mlp_output": 84.7991943359375,
    "active_mlp_output": 4981,
    "total_mlp_output": 32768,
    "sparsity_attention_blocks": 5.008162498474121,
    "sparsity_mlp_blocks": 8.953545570373535,
    "sparsity_attention_heads": 1.0937329530715942,
    "sparsity_attention_neurons": 0.9793209433555603,
    "sparsity_mlp_hidden": 2.4384279251098633,
    "sparsity_mlp_output": 2.569108247756958,
    "sparsity_total_sparsity": 21.04229736328125
  },
  {
    "model": "meta-llama/Llama-3.2-1B",
    "model_short": "Llama-3.2-1B",
    "task": "ioi",
    "lambda_sparsity": 0.85,
    "seed": 42,
    "num_epochs": 500,
    "learning_rate": 0.01,
    "batch_size": 32,
    "training_time_seconds": 364.90237188339233,
    "baseline_accuracy": 1.0,
    "baseline_logit_diff": 5.87525025025025,
    "final_accuracy": 0.6536536536536537,
    "final_logit_diff": 1.1507757757757757,
    "final_kl_div": 1.1601649256678555,
    "final_exact_match": 0.37537537537537535,
    "accuracy_drop": 0.3463463463463463,
    "final_train_loss": 17.056270326886857,
    "final_train_kl": 0.48184884446007864,
    "final_train_sparsity": 19.76663534981864,
    "final_train_task_loss": 1.2156808035714286,
    "compression_ratio": 17.092499531179858,
    "reduction_percentage": 94.14948060594756,
    "active_prunable_params": 56930148,
    "total_prunable_params": 973078528,
    "effective_compression": 3.8641883786483553,
    "pruned_pct_embedding": 100.0,
    "active_embedding": 0,
    "total_embedding": 1,
    "pruned_pct_layer_level": 0.0,
    "active_layer_level": 16,
    "total_layer_level": 16,
    "pruned_pct_attention_blocks": 68.75,
    "active_attention_blocks": 5,
    "total_attention_blocks": 16,
    "pruned_pct_mlp_blocks": 50.0,
    "active_mlp_blocks": 8,
    "total_mlp_blocks": 16,
    "pruned_pct_attention_heads": 93.359375,
    "active_attention_heads": 34,
    "total_attention_heads": 512,
    "pruned_pct_attention_neurons": 94.5037841796875,
    "active_attention_neurons": 1801,
    "total_attention_neurons": 32768,
    "pruned_pct_mlp_hidden": 88.16452026367188,
    "active_mlp_hidden": 15513,
    "total_mlp_hidden": 131072,
    "pruned_pct_mlp_output": 85.9710693359375,
    "active_mlp_output": 4597,
    "total_mlp_output": 32768,
    "sparsity_attention_blocks": 5.008162021636963,
    "sparsity_mlp_blocks": 8.015209197998047,
    "sparsity_attention_heads": 1.0915077924728394,
    "sparsity_attention_neurons": 0.9551835656166077,
    "sparsity_mlp_hidden": 2.239910125732422,
    "sparsity_mlp_output": 2.4528064727783203,
    "sparsity_total_sparsity": 19.762773513793945
  },
  {
    "model": "meta-llama/Llama-3.2-1B",
    "model_short": "Llama-3.2-1B",
    "task": "ioi",
    "lambda_sparsity": 0.88,
    "seed": 42,
    "num_epochs": 500,
    "learning_rate": 0.01,
    "batch_size": 32,
    "training_time_seconds": 365.3352997303009,
    "baseline_accuracy": 1.0,
    "baseline_logit_diff": 5.87525025025025,
    "final_accuracy": 0.2702702702702703,
    "final_logit_diff": -1.6499624624624625,
    "final_kl_div": 1.8373640974959333,
    "final_exact_match": 0.2022022022022022,
    "accuracy_drop": 0.7297297297297297,
    "final_train_loss": 15.652210235595703,
    "final_train_kl": 1.2177854350634985,
    "final_train_sparsity": 17.044610159737722,
    "final_train_task_loss": 4.223493303571429,
    "compression_ratio": 20.26389475070247,
    "reduction_percentage": 95.06511451869176,
    "active_prunable_params": 48020311,
    "total_prunable_params": 973078528,
    "effective_compression": 3.9749101002566833,
    "pruned_pct_embedding": 100.0,
    "active_embedding": 0,
    "total_embedding": 1,
    "pruned_pct_layer_level": 0.0,
    "active_layer_level": 16,
    "total_layer_level": 16,
    "pruned_pct_attention_blocks": 75.0,
    "active_attention_blocks": 4,
    "total_attention_blocks": 16,
    "pruned_pct_mlp_blocks": 56.25,
    "active_mlp_blocks": 7,
    "total_mlp_blocks": 16,
    "pruned_pct_attention_heads": 94.140625,
    "active_attention_heads": 30,
    "total_attention_heads": 512,
    "pruned_pct_attention_neurons": 95.25146484375,
    "active_attention_neurons": 1556,
    "total_attention_neurons": 32768,
    "pruned_pct_mlp_hidden": 90.09017944335938,
    "active_mlp_hidden": 12989,
    "total_mlp_hidden": 131072,
    "pruned_pct_mlp_output": 87.6068115234375,
    "active_mlp_output": 4061,
    "total_mlp_output": 32768,
    "sparsity_attention_blocks": 4.0241827964782715,
    "sparsity_mlp_blocks": 7.013864994049072,
    "sparsity_attention_heads": 1.0877705812454224,
    "sparsity_attention_neurons": 0.9195178747177124,
    "sparsity_mlp_hidden": 1.8131016492843628,
    "sparsity_mlp_output": 2.1829891204833984,
    "sparsity_total_sparsity": 17.04142951965332
  },
  {
    "model": "meta-llama/Llama-3.2-1B",
    "model_short": "Llama-3.2-1B",
    "task": "ioi",
    "lambda_sparsity": 0.9,
    "seed": 42,
    "num_epochs": 500,
    "learning_rate": 0.01,
    "batch_size": 32,
    "training_time_seconds": 364.99902057647705,
    "baseline_accuracy": 1.0,
    "baseline_logit_diff": 5.87525025025025,
    "final_accuracy": 0.036036036036036036,
    "final_logit_diff": -3.718093093093093,
    "final_kl_div": 3.1044015206612863,
    "final_exact_match": 0.1871871871871872,
    "accuracy_drop": 0.963963963963964,
    "final_train_loss": 11.231134687151227,
    "final_train_kl": 2.9476113319396973,
    "final_train_sparsity": 11.32399068559919,
    "final_train_task_loss": 7.447823660714286,
    "compression_ratio": 36.76335295524414,
    "reduction_percentage": 97.2798999013572,
    "active_prunable_params": 26468710,
    "total_prunable_params": 973078528,
    "effective_compression": 4.2709196483252585,
    "pruned_pct_embedding": 100.0,
    "active_embedding": 0,
    "total_embedding": 1,
    "pruned_pct_layer_level": 0.0,
    "active_layer_level": 16,
    "total_layer_level": 16,
    "pruned_pct_attention_blocks": 75.0,
    "active_attention_blocks": 4,
    "total_attention_blocks": 16,
    "pruned_pct_mlp_blocks": 81.25,
    "active_mlp_blocks": 3,
    "total_mlp_blocks": 16,
    "pruned_pct_attention_heads": 94.53125,
    "active_attention_heads": 28,
    "total_attention_heads": 512,
    "pruned_pct_attention_neurons": 95.6207275390625,
    "active_attention_neurons": 1435,
    "total_attention_neurons": 32768,
    "pruned_pct_mlp_hidden": 95.58944702148438,
    "active_mlp_hidden": 5781,
    "total_mlp_hidden": 131072,
    "pruned_pct_mlp_output": 95.1080322265625,
    "active_mlp_output": 1603,
    "total_mlp_output": 32768,
    "sparsity_attention_blocks": 4.004631042480469,
    "sparsity_mlp_blocks": 3.1331257820129395,
    "sparsity_attention_heads": 0.9630065560340881,
    "sparsity_attention_neurons": 0.8196748495101929,
    "sparsity_mlp_hidden": 1.1249055862426758,
    "sparsity_mlp_output": 1.2696800231933594,
    "sparsity_total_sparsity": 11.315025329589844
  },
  {
    "model": "meta-llama/Llama-3.2-1B",
    "model_short": "Llama-3.2-1B",
    "task": "ioi",
    "lambda_sparsity": 0.93,
    "seed": 42,
    "num_epochs": 500,
    "learning_rate": 0.01,
    "batch_size": 32,
    "training_time_seconds": 366.29775977134705,
    "baseline_accuracy": 1.0,
    "baseline_logit_diff": 5.87525025025025,
    "final_accuracy": 0.0,
    "final_logit_diff": -6.915071321321322,
    "final_kl_div": 3.4117822656641015,
    "final_exact_match": 0.1881881881881882,
    "accuracy_drop": 1.0,
    "final_train_loss": 2.304964917046683,
    "final_train_kl": 3.2538911615099226,
    "final_train_sparsity": 1.4330215454101562,
    "final_train_task_loss": 10.635463169642858,
    "compression_ratio": Infinity,
    "reduction_percentage": 100.0,
    "active_prunable_params": 0,
    "total_prunable_params": 973078528,
    "effective_compression": 4.700860824542146,
    "pruned_pct_embedding": 100.0,
    "active_embedding": 0,
    "total_embedding": 1,
    "pruned_pct_layer_level": 0.0,
    "active_layer_level": 16,
    "total_layer_level": 16,
    "pruned_pct_attention_blocks": 100.0,
    "active_attention_blocks": 0,
    "total_attention_blocks": 16,
    "pruned_pct_mlp_blocks": 100.0,
    "active_mlp_blocks": 0,
    "total_mlp_blocks": 16,
    "pruned_pct_attention_heads": 100.0,
    "active_attention_heads": 0,
    "total_attention_heads": 512,
    "pruned_pct_attention_neurons": 100.0,
    "active_attention_neurons": 0,
    "total_attention_neurons": 32768,
    "pruned_pct_mlp_hidden": 100.0,
    "active_mlp_hidden": 0,
    "total_mlp_hidden": 131072,
    "pruned_pct_mlp_output": 100.0,
    "active_mlp_output": 0,
    "total_mlp_output": 32768,
    "sparsity_attention_blocks": 0.0336843878030777,
    "sparsity_mlp_blocks": 0.04927396401762962,
    "sparsity_attention_heads": 0.3525698482990265,
    "sparsity_attention_neurons": 0.2762746512889862,
    "sparsity_mlp_hidden": 0.33539947867393494,
    "sparsity_mlp_output": 0.38034915924072266,
    "sparsity_total_sparsity": 1.427551507949829
  },
  {
    "model": "meta-llama/Llama-3.2-1B",
    "model_short": "Llama-3.2-1B",
    "task": "ioi",
    "lambda_sparsity": 0.95,
    "seed": 42,
    "num_epochs": 500,
    "learning_rate": 0.01,
    "batch_size": 32,
    "training_time_seconds": 365.52686953544617,
    "baseline_accuracy": 1.0,
    "baseline_logit_diff": 5.87525025025025,
    "final_accuracy": 0.0,
    "final_logit_diff": -6.915071321321322,
    "final_kl_div": 3.4117822656641015,
    "final_exact_match": 0.1881881881881882,
    "accuracy_drop": 1.0,
    "final_train_loss": 1.0347133704594202,
    "final_train_kl": 3.2538911615099226,
    "final_train_sparsity": 0.3581533006259373,
    "final_train_task_loss": 10.635463169642858,
    "compression_ratio": Infinity,
    "reduction_percentage": 100.0,
    "active_prunable_params": 0,
    "total_prunable_params": 973078528,
    "effective_compression": 4.700860824542146,
    "pruned_pct_embedding": 100.0,
    "active_embedding": 0,
    "total_embedding": 1,
    "pruned_pct_layer_level": 0.0,
    "active_layer_level": 16,
    "total_layer_level": 16,
    "pruned_pct_attention_blocks": 100.0,
    "active_attention_blocks": 0,
    "total_attention_blocks": 16,
    "pruned_pct_mlp_blocks": 100.0,
    "active_mlp_blocks": 0,
    "total_mlp_blocks": 16,
    "pruned_pct_attention_heads": 100.0,
    "active_attention_heads": 0,
    "total_attention_heads": 512,
    "pruned_pct_attention_neurons": 100.0,
    "active_attention_neurons": 0,
    "total_attention_neurons": 32768,
    "pruned_pct_mlp_hidden": 100.0,
    "active_mlp_hidden": 0,
    "total_mlp_hidden": 131072,
    "pruned_pct_mlp_output": 100.0,
    "active_mlp_output": 0,
    "total_mlp_output": 32768,
    "sparsity_attention_blocks": 0.025254756212234497,
    "sparsity_mlp_blocks": 0.031118551269173622,
    "sparsity_attention_heads": 0.025896402075886726,
    "sparsity_attention_neurons": 0.04321886599063873,
    "sparsity_mlp_hidden": 0.13766597211360931,
    "sparsity_mlp_output": 0.09396965056657791,
    "sparsity_total_sparsity": 0.3571242392063141
  },
  {
    "model": "meta-llama/Llama-3.2-1B",
    "model_short": "Llama-3.2-1B",
    "task": "gp",
    "lambda_sparsity": 0.7,
    "seed": 42,
    "num_epochs": 500,
    "learning_rate": 0.01,
    "batch_size": 32,
    "training_time_seconds": 260.7612636089325,
    "baseline_accuracy": 1.0,
    "baseline_logit_diff": 4.617788461538462,
    "final_accuracy": 0.9911242603550295,
    "final_logit_diff": 10.775147928994082,
    "final_kl_div": 0.7921917255108173,
    "final_exact_match": 0.849112426035503,
    "accuracy_drop": 0.00887573964497046,
    "final_train_loss": 15.089124488830567,
    "final_train_kl": 0.8533353567123413,
    "final_train_sparsity": 20.67488670349121,
    "final_train_task_loss": 1.20234375,
    "compression_ratio": 12.782501056934262,
    "reduction_percentage": 92.17680487139471,
    "active_prunable_params": 76125832,
    "total_prunable_params": 973078528,
    "effective_compression": 3.6454188708759165,
    "pruned_pct_embedding": 100.0,
    "active_embedding": 0,
    "total_embedding": 1,
    "pruned_pct_layer_level": 0.0,
    "active_layer_level": 16,
    "total_layer_level": 16,
    "pruned_pct_attention_blocks": 68.75,
    "active_attention_blocks": 5,
    "total_attention_blocks": 16,
    "pruned_pct_mlp_blocks": 68.75,
    "active_mlp_blocks": 5,
    "total_mlp_blocks": 16,
    "pruned_pct_attention_heads": 95.8984375,
    "active_attention_heads": 21,
    "total_attention_heads": 512,
    "pruned_pct_attention_neurons": 97.3358154296875,
    "active_attention_neurons": 873,
    "total_attention_neurons": 32768,
    "pruned_pct_mlp_hidden": 83.99505615234375,
    "active_mlp_hidden": 20978,
    "total_mlp_hidden": 131072,
    "pruned_pct_mlp_output": 83.502197265625,
    "active_mlp_output": 5406,
    "total_mlp_output": 32768,
    "sparsity_attention_blocks": 5.013766765594482,
    "sparsity_mlp_blocks": 5.037123680114746,
    "sparsity_attention_heads": 0.8766376972198486,
    "sparsity_attention_neurons": 0.9217461347579956,
    "sparsity_mlp_hidden": 4.938284873962402,
    "sparsity_mlp_output": 3.8627736568450928,
    "sparsity_total_sparsity": 20.65033531188965
  },
  {
    "model": "meta-llama/Llama-3.2-1B",
    "model_short": "Llama-3.2-1B",
    "task": "gp",
    "lambda_sparsity": 0.73,
    "seed": 42,
    "num_epochs": 500,
    "learning_rate": 0.01,
    "batch_size": 32,
    "training_time_seconds": 261.1244978904724,
    "baseline_accuracy": 1.0,
    "baseline_logit_diff": 4.617788461538462,
    "final_accuracy": 0.9792899408284024,
    "final_logit_diff": 9.043361686390533,
    "final_kl_div": 0.7340996194873336,
    "final_exact_match": 0.8461538461538461,
    "accuracy_drop": 0.020710059171597628,
    "final_train_loss": 13.768000411987305,
    "final_train_kl": 0.9100674390792847,
    "final_train_sparsity": 18.10428123474121,
    "final_train_task_loss": 1.1339133530855179,
    "compression_ratio": 14.41512332239023,
    "reduction_percentage": 93.06284117287603,
    "active_prunable_params": 67504003,
    "total_prunable_params": 973078528,
    "effective_compression": 3.7405358691839337,
    "pruned_pct_embedding": 100.0,
    "active_embedding": 0,
    "total_embedding": 1,
    "pruned_pct_layer_level": 0.0,
    "active_layer_level": 16,
    "total_layer_level": 16,
    "pruned_pct_attention_blocks": 75.0,
    "active_attention_blocks": 4,
    "total_attention_blocks": 16,
    "pruned_pct_mlp_blocks": 68.75,
    "active_mlp_blocks": 5,
    "total_mlp_blocks": 16,
    "pruned_pct_attention_heads": 97.0703125,
    "active_attention_heads": 15,
    "total_attention_heads": 512,
    "pruned_pct_attention_neurons": 98.0224609375,
    "active_attention_neurons": 648,
    "total_attention_neurons": 32768,
    "pruned_pct_mlp_hidden": 85.26458740234375,
    "active_mlp_hidden": 19314,
    "total_mlp_hidden": 131072,
    "pruned_pct_mlp_output": 84.4390869140625,
    "active_mlp_output": 5099,
    "total_mlp_output": 32768,
    "sparsity_attention_blocks": 4.047120094299316,
    "sparsity_mlp_blocks": 5.032435894012451,
    "sparsity_attention_heads": 0.7302907109260559,
    "sparsity_attention_neurons": 0.7762285470962524,
    "sparsity_mlp_hidden": 4.146255016326904,
    "sparsity_mlp_output": 3.3510053157806396,
    "sparsity_total_sparsity": 18.08333396911621
  },
  {
    "model": "meta-llama/Llama-3.2-1B",
    "model_short": "Llama-3.2-1B",
    "task": "gp",
    "lambda_sparsity": 0.75,
    "seed": 42,
    "num_epochs": 500,
    "learning_rate": 0.01,
    "batch_size": 32,
    "training_time_seconds": 261.0706877708435,
    "baseline_accuracy": 1.0,
    "baseline_logit_diff": 4.617788461538462,
    "final_accuracy": 0.9763313609467456,
    "final_logit_diff": 9.03698224852071,
    "final_kl_div": 0.7541625795985115,
    "final_exact_match": 0.849112426035503,
    "accuracy_drop": 0.023668639053254448,
    "final_train_loss": 13.457120513916015,
    "final_train_kl": 1.0002303719520569,
    "final_train_sparsity": 17.193093490600585,
    "final_train_task_loss": 1.2489701703190803,
    "compression_ratio": 15.465902891790314,
    "reduction_percentage": 93.53416346270463,
    "active_prunable_params": 62917667,
    "total_prunable_params": 973078528,
    "effective_compression": 3.793183768329035,
    "pruned_pct_embedding": 100.0,
    "active_embedding": 0,
    "total_embedding": 1,
    "pruned_pct_layer_level": 0.0,
    "active_layer_level": 16,
    "total_layer_level": 16,
    "pruned_pct_attention_blocks": 75.0,
    "active_attention_blocks": 4,
    "total_attention_blocks": 16,
    "pruned_pct_mlp_blocks": 68.75,
    "active_mlp_blocks": 5,
    "total_mlp_blocks": 16,
    "pruned_pct_attention_heads": 97.0703125,
    "active_attention_heads": 15,
    "total_attention_heads": 512,
    "pruned_pct_attention_neurons": 98.0682373046875,
    "active_attention_neurons": 633,
    "total_attention_neurons": 32768,
    "pruned_pct_mlp_hidden": 86.09161376953125,
    "active_mlp_hidden": 18230,
    "total_mlp_hidden": 131072,
    "pruned_pct_mlp_output": 85.29052734375,
    "active_mlp_output": 4820,
    "total_mlp_output": 32768,
    "sparsity_attention_blocks": 4.045137882232666,
    "sparsity_mlp_blocks": 5.019404411315918,
    "sparsity_attention_heads": 0.7425187230110168,
    "sparsity_attention_neurons": 0.7022297382354736,
    "sparsity_mlp_hidden": 3.6745007038116455,
    "sparsity_mlp_output": 2.9918408393859863,
    "sparsity_total_sparsity": 17.175630569458008
  },
  {
    "model": "meta-llama/Llama-3.2-1B",
    "model_short": "Llama-3.2-1B",
    "task": "gp",
    "lambda_sparsity": 0.78,
    "seed": 42,
    "num_epochs": 500,
    "learning_rate": 0.01,
    "batch_size": 32,
    "training_time_seconds": 261.1569917201996,
    "baseline_accuracy": 1.0,
    "baseline_logit_diff": 4.617788461538462,
    "final_accuracy": 0.9733727810650887,
    "final_logit_diff": 8.331360946745562,
    "final_kl_div": 0.803089661005686,
    "final_exact_match": 0.8165680473372781,
    "accuracy_drop": 0.026627218934911268,
    "final_train_loss": 11.89956111907959,
    "final_train_kl": 1.2043612360954286,
    "final_train_sparsity": 14.569221305847169,
    "final_train_task_loss": 1.2300426136702298,
    "compression_ratio": 24.315524569354462,
    "reduction_percentage": 95.88740108342006,
    "active_prunable_params": 40018817,
    "total_prunable_params": 973078528,
    "effective_compression": 4.079894507061272,
    "pruned_pct_embedding": 100.0,
    "active_embedding": 0,
    "total_embedding": 1,
    "pruned_pct_layer_level": 0.0,
    "active_layer_level": 16,
    "total_layer_level": 16,
    "pruned_pct_attention_blocks": 68.75,
    "active_attention_blocks": 5,
    "total_attention_blocks": 16,
    "pruned_pct_mlp_blocks": 81.25,
    "active_mlp_blocks": 3,
    "total_mlp_blocks": 16,
    "pruned_pct_attention_heads": 96.484375,
    "active_attention_heads": 18,
    "total_attention_heads": 512,
    "pruned_pct_attention_neurons": 97.772216796875,
    "active_attention_neurons": 730,
    "total_attention_neurons": 32768,
    "pruned_pct_mlp_hidden": 91.72897338867188,
    "active_mlp_hidden": 10841,
    "total_mlp_hidden": 131072,
    "pruned_pct_mlp_output": 90.8477783203125,
    "active_mlp_output": 2999,
    "total_mlp_output": 32768,
    "sparsity_attention_blocks": 5.017476558685303,
    "sparsity_mlp_blocks": 3.059380531311035,
    "sparsity_attention_heads": 0.7504878640174866,
    "sparsity_attention_neurons": 0.6291432976722717,
    "sparsity_mlp_hidden": 2.8759469985961914,
    "sparsity_mlp_output": 2.220771551132202,
    "sparsity_total_sparsity": 14.553205490112305
  },
  {
    "model": "meta-llama/Llama-3.2-1B",
    "model_short": "Llama-3.2-1B",
    "task": "gp",
    "lambda_sparsity": 0.8,
    "seed": 42,
    "num_epochs": 500,
    "learning_rate": 0.01,
    "batch_size": 32,
    "training_time_seconds": 260.8801791667938,
    "baseline_accuracy": 1.0,
    "baseline_logit_diff": 4.617788461538462,
    "final_accuracy": 0.9763313609467456,
    "final_logit_diff": 8.13590976331361,
    "final_kl_div": 0.8010990661982249,
    "final_exact_match": 0.8165680473372781,
    "accuracy_drop": 0.023668639053254448,
    "final_train_loss": 11.401108169555664,
    "final_train_kl": 1.2434130787849427,
    "final_train_sparsity": 13.637646102905274,
    "final_train_task_loss": 1.2115411933511495,
    "compression_ratio": 26.671907278060974,
    "reduction_percentage": 96.25073681617606,
    "active_prunable_params": 36483275,
    "total_prunable_params": 973078528,
    "effective_compression": 4.1280703693421845,
    "pruned_pct_embedding": 100.0,
    "active_embedding": 0,
    "total_embedding": 1,
    "pruned_pct_layer_level": 0.0,
    "active_layer_level": 16,
    "total_layer_level": 16,
    "pruned_pct_attention_blocks": 68.75,
    "active_attention_blocks": 5,
    "total_attention_blocks": 16,
    "pruned_pct_mlp_blocks": 81.25,
    "active_mlp_blocks": 3,
    "total_mlp_blocks": 16,
    "pruned_pct_attention_heads": 96.6796875,
    "active_attention_heads": 17,
    "total_attention_heads": 512,
    "pruned_pct_attention_neurons": 97.91259765625,
    "active_attention_neurons": 684,
    "total_attention_neurons": 32768,
    "pruned_pct_mlp_hidden": 92.32025146484375,
    "active_mlp_hidden": 10066,
    "total_mlp_hidden": 131072,
    "pruned_pct_mlp_output": 91.5008544921875,
    "active_mlp_output": 2785,
    "total_mlp_output": 32768,
    "sparsity_attention_blocks": 5.01475715637207,
    "sparsity_mlp_blocks": 3.0499730110168457,
    "sparsity_attention_heads": 0.6618297696113586,
    "sparsity_attention_neurons": 0.5798709392547607,
    "sparsity_mlp_hidden": 2.438610553741455,
    "sparsity_mlp_output": 1.879172682762146,
    "sparsity_total_sparsity": 13.624216079711914
  },
  {
    "model": "meta-llama/Llama-3.2-1B",
    "model_short": "Llama-3.2-1B",
    "task": "gp",
    "lambda_sparsity": 0.83,
    "seed": 42,
    "num_epochs": 500,
    "learning_rate": 0.01,
    "batch_size": 32,
    "training_time_seconds": 261.06969690322876,
    "baseline_accuracy": 1.0,
    "baseline_logit_diff": 4.617788461538462,
    "final_accuracy": 0.9644970414201184,
    "final_logit_diff": 5.886649408284024,
    "final_kl_div": 0.7528951972193972,
    "final_exact_match": 0.7869822485207101,
    "accuracy_drop": 0.035502958579881616,
    "final_train_loss": 10.143147850036621,
    "final_train_kl": 1.3949352622032165,
    "final_train_sparsity": 11.582102966308593,
    "final_train_task_loss": 1.7227272748947144,
    "compression_ratio": 30.69171227892396,
    "reduction_percentage": 96.7417914291908,
    "active_prunable_params": 31704928,
    "total_prunable_params": 973078528,
    "effective_compression": 4.195018135341913,
    "pruned_pct_embedding": 100.0,
    "active_embedding": 0,
    "total_embedding": 1,
    "pruned_pct_layer_level": 0.0,
    "active_layer_level": 16,
    "total_layer_level": 16,
    "pruned_pct_attention_blocks": 75.0,
    "active_attention_blocks": 4,
    "total_attention_blocks": 16,
    "pruned_pct_mlp_blocks": 81.25,
    "active_mlp_blocks": 3,
    "total_mlp_blocks": 16,
    "pruned_pct_attention_heads": 97.265625,
    "active_attention_heads": 14,
    "total_attention_heads": 512,
    "pruned_pct_attention_neurons": 98.3154296875,
    "active_attention_neurons": 552,
    "total_attention_neurons": 32768,
    "pruned_pct_mlp_hidden": 93.16558837890625,
    "active_mlp_hidden": 8958,
    "total_mlp_hidden": 131072,
    "pruned_pct_mlp_output": 91.7755126953125,
    "active_mlp_output": 2695,
    "total_mlp_output": 32768,
    "sparsity_attention_blocks": 4.038207530975342,
    "sparsity_mlp_blocks": 3.0420682430267334,
    "sparsity_attention_heads": 0.5903468728065491,
    "sparsity_attention_neurons": 0.49469295144081116,
    "sparsity_mlp_hidden": 1.820700764656067,
    "sparsity_mlp_output": 1.5870819091796875,
    "sparsity_total_sparsity": 11.573098182678223
  },
  {
    "model": "meta-llama/Llama-3.2-1B",
    "model_short": "Llama-3.2-1B",
    "task": "gp",
    "lambda_sparsity": 0.85,
    "seed": 42,
    "num_epochs": 500,
    "learning_rate": 0.01,
    "batch_size": 32,
    "training_time_seconds": 261.0813522338867,
    "baseline_accuracy": 1.0,
    "baseline_logit_diff": 4.617788461538462,
    "final_accuracy": 0.9615384615384616,
    "final_logit_diff": 5.671227810650888,
    "final_kl_div": 0.7595286171817215,
    "final_exact_match": 0.7840236686390533,
    "accuracy_drop": 0.038461538461538436,
    "final_train_loss": 9.901340866088868,
    "final_train_kl": 1.4307098150253297,
    "final_train_sparsity": 11.086018562316895,
    "final_train_task_loss": 1.7574573874473571,
    "compression_ratio": 33.96142691118735,
    "reduction_percentage": 97.05548296714652,
    "active_prunable_params": 28652463,
    "total_prunable_params": 973078528,
    "effective_compression": 4.238933716203784,
    "pruned_pct_embedding": 100.0,
    "active_embedding": 0,
    "total_embedding": 1,
    "pruned_pct_layer_level": 0.0,
    "active_layer_level": 16,
    "total_layer_level": 16,
    "pruned_pct_attention_blocks": 75.0,
    "active_attention_blocks": 4,
    "total_attention_blocks": 16,
    "pruned_pct_mlp_blocks": 81.25,
    "active_mlp_blocks": 3,
    "total_mlp_blocks": 16,
    "pruned_pct_attention_heads": 97.265625,
    "active_attention_heads": 14,
    "total_attention_heads": 512,
    "pruned_pct_attention_neurons": 98.3642578125,
    "active_attention_neurons": 536,
    "total_attention_neurons": 32768,
    "pruned_pct_mlp_hidden": 93.78433227539062,
    "active_mlp_hidden": 8147,
    "total_mlp_hidden": 131072,
    "pruned_pct_mlp_output": 92.2698974609375,
    "active_mlp_output": 2533,
    "total_mlp_output": 32768,
    "sparsity_attention_blocks": 4.028584003448486,
    "sparsity_mlp_blocks": 3.0394785404205322,
    "sparsity_attention_heads": 0.5769765973091125,
    "sparsity_attention_neurons": 0.44744744896888733,
    "sparsity_mlp_hidden": 1.531224012374878,
    "sparsity_mlp_output": 1.455674171447754,
    "sparsity_total_sparsity": 11.079380989074707
  },
  {
    "model": "meta-llama/Llama-3.2-1B",
    "model_short": "Llama-3.2-1B",
    "task": "gp",
    "lambda_sparsity": 0.88,
    "seed": 42,
    "num_epochs": 500,
    "learning_rate": 0.01,
    "batch_size": 32,
    "training_time_seconds": 261.0962550640106,
    "baseline_accuracy": 1.0,
    "baseline_logit_diff": 4.617788461538462,
    "final_accuracy": 0.8402366863905325,
    "final_logit_diff": 2.7239275147928996,
    "final_kl_div": 0.8379451593703772,
    "final_exact_match": 0.6538461538461539,
    "accuracy_drop": 0.1597633136094675,
    "final_train_loss": 9.04346160888672,
    "final_train_kl": 1.65361887216568,
    "final_train_sparsity": 9.675097274780274,
    "final_train_task_loss": 2.757848024368286,
    "compression_ratio": 36.09505059205201,
    "reduction_percentage": 97.22953705952085,
    "active_prunable_params": 26958780,
    "total_prunable_params": 973078528,
    "effective_compression": 4.263699542191955,
    "pruned_pct_embedding": 100.0,
    "active_embedding": 0,
    "total_embedding": 1,
    "pruned_pct_layer_level": 0.0,
    "active_layer_level": 16,
    "total_layer_level": 16,
    "pruned_pct_attention_blocks": 81.25,
    "active_attention_blocks": 3,
    "total_attention_blocks": 16,
    "pruned_pct_mlp_blocks": 81.25,
    "active_mlp_blocks": 3,
    "total_mlp_blocks": 16,
    "pruned_pct_attention_heads": 98.046875,
    "active_attention_heads": 10,
    "total_attention_heads": 512,
    "pruned_pct_attention_neurons": 98.81591796875,
    "active_attention_neurons": 388,
    "total_attention_neurons": 32768,
    "pruned_pct_mlp_hidden": 93.99795532226562,
    "active_mlp_hidden": 7867,
    "total_mlp_hidden": 131072,
    "pruned_pct_mlp_output": 91.845703125,
    "active_mlp_output": 2672,
    "total_mlp_output": 32768,
    "sparsity_attention_blocks": 3.036130428314209,
    "sparsity_mlp_blocks": 3.036306858062744,
    "sparsity_attention_heads": 0.4888306260108948,
    "sparsity_attention_neurons": 0.36080196499824524,
    "sparsity_mlp_hidden": 1.2906674146652222,
    "sparsity_mlp_output": 1.4576642513275146,
    "sparsity_total_sparsity": 9.67039680480957
  },
  {
    "model": "meta-llama/Llama-3.2-1B",
    "model_short": "Llama-3.2-1B",
    "task": "gp",
    "lambda_sparsity": 0.9,
    "seed": 42,
    "num_epochs": 500,
    "learning_rate": 0.01,
    "batch_size": 32,
    "training_time_seconds": 261.09871196746826,
    "baseline_accuracy": 1.0,
    "baseline_logit_diff": 4.617788461538462,
    "final_accuracy": 0.8195266272189349,
    "final_logit_diff": 2.304733727810651,
    "final_kl_div": 0.8781535583134938,
    "final_exact_match": 0.6272189349112426,
    "accuracy_drop": 0.18047337278106512,
    "final_train_loss": 8.779215812683105,
    "final_train_kl": 1.7143602132797242,
    "final_train_sparsity": 9.230570983886718,
    "final_train_task_loss": 3.0026633501052857,
    "compression_ratio": 41.75135449256804,
    "reduction_percentage": 97.60486812427126,
    "active_prunable_params": 23306514,
    "total_prunable_params": 973078528,
    "effective_compression": 4.3181021064951555,
    "pruned_pct_embedding": 100.0,
    "active_embedding": 0,
    "total_embedding": 1,
    "pruned_pct_layer_level": 0.0,
    "active_layer_level": 16,
    "total_layer_level": 16,
    "pruned_pct_attention_blocks": 81.25,
    "active_attention_blocks": 3,
    "total_attention_blocks": 16,
    "pruned_pct_mlp_blocks": 81.25,
    "active_mlp_blocks": 3,
    "total_mlp_blocks": 16,
    "pruned_pct_attention_heads": 98.046875,
    "active_attention_heads": 10,
    "total_attention_heads": 512,
    "pruned_pct_attention_neurons": 98.8800048828125,
    "active_attention_neurons": 367,
    "total_attention_neurons": 32768,
    "pruned_pct_mlp_hidden": 94.7418212890625,
    "active_mlp_hidden": 6892,
    "total_mlp_hidden": 131072,
    "pruned_pct_mlp_output": 92.5750732421875,
    "active_mlp_output": 2433,
    "total_mlp_output": 32768,
    "sparsity_attention_blocks": 3.0328807830810547,
    "sparsity_mlp_blocks": 3.032094955444336,
    "sparsity_attention_heads": 0.4510732889175415,
    "sparsity_attention_neurons": 0.32601165771484375,
    "sparsity_mlp_hidden": 1.080182433128357,
    "sparsity_mlp_output": 1.3046016693115234,
    "sparsity_total_sparsity": 9.226844787597656
  },
  {
    "model": "meta-llama/Llama-3.2-1B",
    "model_short": "Llama-3.2-1B",
    "task": "gp",
    "lambda_sparsity": 0.93,
    "seed": 42,
    "num_epochs": 500,
    "learning_rate": 0.01,
    "batch_size": 32,
    "training_time_seconds": 260.81104135513306,
    "baseline_accuracy": 1.0,
    "baseline_logit_diff": 4.617788461538462,
    "final_accuracy": 0.7366863905325444,
    "final_logit_diff": 1.7074704142011834,
    "final_kl_div": 0.9528370242147051,
    "final_exact_match": 0.5798816568047337,
    "accuracy_drop": 0.26331360946745563,
    "final_train_loss": 8.360751152038574,
    "final_train_kl": 1.800824236869812,
    "final_train_sparsity": 8.598749923706055,
    "final_train_task_loss": 3.3979403495788576,
    "compression_ratio": 53.85406703476705,
    "reduction_percentage": 98.14313002701464,
    "active_prunable_params": 18068803,
    "total_prunable_params": 973078528,
    "effective_compression": 4.398589024120473,
    "pruned_pct_embedding": 100.0,
    "active_embedding": 0,
    "total_embedding": 1,
    "pruned_pct_layer_level": 0.0,
    "active_layer_level": 16,
    "total_layer_level": 16,
    "pruned_pct_attention_blocks": 81.25,
    "active_attention_blocks": 3,
    "total_attention_blocks": 16,
    "pruned_pct_mlp_blocks": 81.25,
    "active_mlp_blocks": 3,
    "total_mlp_blocks": 16,
    "pruned_pct_attention_heads": 98.2421875,
    "active_attention_heads": 9,
    "total_attention_heads": 512,
    "pruned_pct_attention_neurons": 99.017333984375,
    "active_attention_neurons": 322,
    "total_attention_neurons": 32768,
    "pruned_pct_mlp_hidden": 95.84121704101562,
    "active_mlp_hidden": 5451,
    "total_mlp_hidden": 131072,
    "pruned_pct_mlp_output": 93.56689453125,
    "active_mlp_output": 2108,
    "total_mlp_output": 32768,
    "sparsity_attention_blocks": 3.019339084625244,
    "sparsity_mlp_blocks": 3.0194733142852783,
    "sparsity_attention_heads": 0.37993571162223816,
    "sparsity_attention_neurons": 0.2570028305053711,
    "sparsity_mlp_hidden": 0.8093662261962891,
    "sparsity_mlp_output": 1.1118212938308716,
    "sparsity_total_sparsity": 8.596939086914062
  },
  {
    "model": "meta-llama/Llama-3.2-1B",
    "model_short": "Llama-3.2-1B",
    "task": "gp",
    "lambda_sparsity": 0.95,
    "seed": 42,
    "num_epochs": 500,
    "learning_rate": 0.01,
    "batch_size": 32,
    "training_time_seconds": 260.84956073760986,
    "baseline_accuracy": 1.0,
    "baseline_logit_diff": 4.617788461538462,
    "final_accuracy": 0.07988165680473373,
    "final_logit_diff": -3.8276627218934913,
    "final_kl_div": 3.1536973580806213,
    "final_exact_match": 0.07692307692307693,
    "accuracy_drop": 0.9201183431952663,
    "final_train_loss": 1.9294766664505005,
    "final_train_kl": 3.805629920959473,
    "final_train_sparsity": 1.407587742805481,
    "final_train_task_loss": 8.039737319946289,
    "compression_ratio": Infinity,
    "reduction_percentage": 100.0,
    "active_prunable_params": 0,
    "total_prunable_params": 973078528,
    "effective_compression": 4.700860824542146,
    "pruned_pct_embedding": 100.0,
    "active_embedding": 0,
    "total_embedding": 1,
    "pruned_pct_layer_level": 0.0,
    "active_layer_level": 16,
    "total_layer_level": 16,
    "pruned_pct_attention_blocks": 100.0,
    "active_attention_blocks": 0,
    "total_attention_blocks": 16,
    "pruned_pct_mlp_blocks": 100.0,
    "active_mlp_blocks": 0,
    "total_mlp_blocks": 16,
    "pruned_pct_attention_heads": 100.0,
    "active_attention_heads": 0,
    "total_attention_heads": 512,
    "pruned_pct_attention_neurons": 100.0,
    "active_attention_neurons": 0,
    "total_attention_neurons": 32768,
    "pruned_pct_mlp_hidden": 100.0,
    "active_mlp_hidden": 0,
    "total_mlp_hidden": 131072,
    "pruned_pct_mlp_output": 100.0,
    "active_mlp_output": 0,
    "total_mlp_output": 32768,
    "sparsity_attention_blocks": 0.11048681288957596,
    "sparsity_mlp_blocks": 0.05974740535020828,
    "sparsity_attention_heads": 0.2507384419441223,
    "sparsity_attention_neurons": 0.18579316139221191,
    "sparsity_mlp_hidden": 0.3482702076435089,
    "sparsity_mlp_output": 0.44706296920776367,
    "sparsity_total_sparsity": 1.4020990133285522
  },
  {
    "model": "meta-llama/Llama-3.1-8B",
    "model_short": "Llama-3.1-8B",
    "task": "ioi",
    "lambda_sparsity": 0.7,
    "seed": 42,
    "num_epochs": 500,
    "learning_rate": 0.01,
    "batch_size": 32,
    "training_time_seconds": 1138.5557460784912,
    "baseline_accuracy": 1.0,
    "baseline_logit_diff": 5.808390625,
    "final_accuracy": 0.834,
    "final_logit_diff": 2.99755859375,
    "final_kl_div": 0.952024658203125,
    "final_exact_match": 0.416,
    "accuracy_drop": 0.16600000000000004,
    "final_train_loss": 31.06772886003767,
    "final_train_kl": 0.4172165095806122,
    "final_train_sparsity": 43.813895089285715,
    "final_train_task_loss": 0.9094587053571429,
    "compression_ratio": 15.815370806809506,
    "reduction_percentage": 93.67703728091257,
    "active_prunable_params": 441299919,
    "total_prunable_params": 6979321856,
    "effective_compression": 5.3792307000162385,
    "pruned_pct_embedding": 100.0,
    "active_embedding": 0,
    "total_embedding": 1,
    "pruned_pct_layer_level": 0.0,
    "active_layer_level": 32,
    "total_layer_level": 32,
    "pruned_pct_attention_blocks": 71.875,
    "active_attention_blocks": 9,
    "total_attention_blocks": 32,
    "pruned_pct_mlp_blocks": 43.75,
    "active_mlp_blocks": 18,
    "total_mlp_blocks": 32,
    "pruned_pct_attention_heads": 95.703125,
    "active_attention_heads": 44,
    "total_attention_heads": 1024,
    "pruned_pct_attention_neurons": 96.533203125,
    "active_attention_neurons": 4544,
    "total_attention_neurons": 131072,
    "pruned_pct_mlp_hidden": 86.50360107421875,
    "active_mlp_hidden": 61915,
    "total_mlp_hidden": 458752,
    "pruned_pct_mlp_output": 76.4984130859375,
    "active_mlp_output": 30804,
    "total_mlp_output": 131072,
    "sparsity_attention_blocks": 9.045101165771484,
    "sparsity_mlp_blocks": 17.99169158935547,
    "sparsity_attention_heads": 1.8692606687545776,
    "sparsity_attention_neurons": 1.6701093912124634,
    "sparsity_mlp_hidden": 5.200538635253906,
    "sparsity_mlp_output": 8.019850730895996,
    "sparsity_total_sparsity": 43.796546936035156
  },
  {
    "model": "meta-llama/Llama-3.1-8B",
    "model_short": "Llama-3.1-8B",
    "task": "ioi",
    "lambda_sparsity": 0.73,
    "seed": 42,
    "num_epochs": 500,
    "learning_rate": 0.01,
    "batch_size": 32,
    "training_time_seconds": 1138.721432685852,
    "baseline_accuracy": 1.0,
    "baseline_logit_diff": 5.808390625,
    "final_accuracy": 0.806,
    "final_logit_diff": 2.7359453125,
    "final_kl_div": 1.01149072265625,
    "final_exact_match": 0.408,
    "accuracy_drop": 0.19399999999999995,
    "final_train_loss": 31.596207209995814,
    "final_train_kl": 0.43000899255275726,
    "final_train_sparsity": 42.78447559901646,
    "final_train_task_loss": 0.9164341517857143,
    "compression_ratio": 16.87431380330504,
    "reduction_percentage": 94.07383309533964,
    "active_prunable_params": 413606262,
    "total_prunable_params": 6979321856,
    "effective_compression": 5.480898522376292,
    "pruned_pct_embedding": 100.0,
    "active_embedding": 0,
    "total_embedding": 1,
    "pruned_pct_layer_level": 0.0,
    "active_layer_level": 32,
    "total_layer_level": 32,
    "pruned_pct_attention_blocks": 71.875,
    "active_attention_blocks": 9,
    "total_attention_blocks": 32,
    "pruned_pct_mlp_blocks": 43.75,
    "active_mlp_blocks": 18,
    "total_mlp_blocks": 32,
    "pruned_pct_attention_heads": 95.80078125,
    "active_attention_heads": 43,
    "total_attention_heads": 1024,
    "pruned_pct_attention_neurons": 96.61788940429688,
    "active_attention_neurons": 4433,
    "total_attention_neurons": 131072,
    "pruned_pct_mlp_hidden": 87.36615862165179,
    "active_mlp_hidden": 57958,
    "total_mlp_hidden": 458752,
    "pruned_pct_mlp_output": 77.1728515625,
    "active_mlp_output": 29920,
    "total_mlp_output": 131072,
    "sparsity_attention_blocks": 8.996560096740723,
    "sparsity_mlp_blocks": 17.989091873168945,
    "sparsity_attention_heads": 1.7153449058532715,
    "sparsity_attention_neurons": 1.5783758163452148,
    "sparsity_mlp_hidden": 4.768187046051025,
    "sparsity_mlp_output": 7.721055030822754,
    "sparsity_total_sparsity": 42.768619537353516
  },
  {
    "model": "meta-llama/Llama-3.1-8B",
    "model_short": "Llama-3.1-8B",
    "task": "ioi",
    "lambda_sparsity": 0.75,
    "seed": 42,
    "num_epochs": 500,
    "learning_rate": 0.01,
    "batch_size": 32,
    "training_time_seconds": 1139.7195608615875,
    "baseline_accuracy": 1.0,
    "baseline_logit_diff": 5.808390625,
    "final_accuracy": 0.764,
    "final_logit_diff": 2.3146953125,
    "final_kl_div": 1.0025908203125,
    "final_exact_match": 0.402,
    "accuracy_drop": 0.236,
    "final_train_loss": 32.093537739345,
    "final_train_kl": 0.4207162324871336,
    "final_train_sparsity": 42.272657666887554,
    "final_train_task_loss": 1.1354631696428572,
    "compression_ratio": 17.37532281096725,
    "reduction_percentage": 94.24471124433555,
    "active_prunable_params": 401680126,
    "total_prunable_params": 6979321856,
    "effective_compression": 5.525874834612684,
    "pruned_pct_embedding": 100.0,
    "active_embedding": 0,
    "total_embedding": 1,
    "pruned_pct_layer_level": 0.0,
    "active_layer_level": 32,
    "total_layer_level": 32,
    "pruned_pct_attention_blocks": 71.875,
    "active_attention_blocks": 9,
    "total_attention_blocks": 32,
    "pruned_pct_mlp_blocks": 43.75,
    "active_mlp_blocks": 18,
    "total_mlp_blocks": 32,
    "pruned_pct_attention_heads": 95.8984375,
    "active_attention_heads": 42,
    "total_attention_heads": 1024,
    "pruned_pct_attention_neurons": 96.6522216796875,
    "active_attention_neurons": 4388,
    "total_attention_neurons": 131072,
    "pruned_pct_mlp_hidden": 87.75700160435268,
    "active_mlp_hidden": 56165,
    "total_mlp_hidden": 458752,
    "pruned_pct_mlp_output": 77.4993896484375,
    "active_mlp_output": 29492,
    "total_mlp_output": 131072,
    "sparsity_attention_blocks": 9.015571594238281,
    "sparsity_mlp_blocks": 17.982440948486328,
    "sparsity_attention_heads": 1.6559380292892456,
    "sparsity_attention_neurons": 1.4622266292572021,
    "sparsity_mlp_hidden": 4.5722503662109375,
    "sparsity_mlp_output": 7.568883895874023,
    "sparsity_total_sparsity": 42.257320404052734
  },
  {
    "model": "meta-llama/Llama-3.1-8B",
    "model_short": "Llama-3.1-8B",
    "task": "ioi",
    "lambda_sparsity": 0.78,
    "seed": 42,
    "num_epochs": 500,
    "learning_rate": 0.01,
    "batch_size": 32,
    "training_time_seconds": 1138.4100134372711,
    "baseline_accuracy": 1.0,
    "baseline_logit_diff": 5.808390625,
    "final_accuracy": 0.611,
    "final_logit_diff": 0.860796875,
    "final_kl_div": 1.12930078125,
    "final_exact_match": 0.361,
    "accuracy_drop": 0.389,
    "final_train_loss": 31.948429925101145,
    "final_train_kl": 0.4700129883629935,
    "final_train_sparsity": 40.32187979561942,
    "final_train_task_loss": 1.7907366071428572,
    "compression_ratio": 16.849223668529834,
    "reduction_percentage": 94.06500845574416,
    "active_prunable_params": 414222162,
    "total_prunable_params": 6979321856,
    "effective_compression": 5.47859568909355,
    "pruned_pct_embedding": 100.0,
    "active_embedding": 0,
    "total_embedding": 1,
    "pruned_pct_layer_level": 0.0,
    "active_layer_level": 32,
    "total_layer_level": 32,
    "pruned_pct_attention_blocks": 78.125,
    "active_attention_blocks": 7,
    "total_attention_blocks": 32,
    "pruned_pct_mlp_blocks": 43.75,
    "active_mlp_blocks": 18,
    "total_mlp_blocks": 32,
    "pruned_pct_attention_heads": 96.38671875,
    "active_attention_heads": 37,
    "total_attention_heads": 1024,
    "pruned_pct_attention_neurons": 96.9696044921875,
    "active_attention_neurons": 3972,
    "total_attention_neurons": 131072,
    "pruned_pct_mlp_hidden": 87.18719482421875,
    "active_mlp_hidden": 58779,
    "total_mlp_hidden": 458752,
    "pruned_pct_mlp_output": 76.3580322265625,
    "active_mlp_output": 30988,
    "total_mlp_output": 131072,
    "sparsity_attention_blocks": 7.0496697425842285,
    "sparsity_mlp_blocks": 17.997392654418945,
    "sparsity_attention_heads": 1.439723014831543,
    "sparsity_attention_neurons": 1.3193386793136597,
    "sparsity_mlp_hidden": 4.632254123687744,
    "sparsity_mlp_output": 7.872874736785889,
    "sparsity_total_sparsity": 40.31127166748047
  },
  {
    "model": "meta-llama/Llama-3.1-8B",
    "model_short": "Llama-3.1-8B",
    "task": "ioi",
    "lambda_sparsity": 0.8,
    "seed": 42,
    "num_epochs": 500,
    "learning_rate": 0.01,
    "batch_size": 32,
    "training_time_seconds": 1138.6486060619354,
    "baseline_accuracy": 1.0,
    "baseline_logit_diff": 5.808390625,
    "final_accuracy": 0.565,
    "final_logit_diff": 0.57621875,
    "final_kl_div": 1.16387353515625,
    "final_exact_match": 0.359,
    "accuracy_drop": 0.43500000000000005,
    "final_train_loss": 32.34383692060198,
    "final_train_kl": 0.5666433487619672,
    "final_train_sparsity": 39.665750231061665,
    "final_train_task_loss": 2.489536830357143,
    "compression_ratio": 17.56775266542358,
    "reduction_percentage": 94.30775228314675,
    "active_prunable_params": 397280289,
    "total_prunable_params": 6979321856,
    "effective_compression": 5.542654632683228,
    "pruned_pct_embedding": 100.0,
    "active_embedding": 0,
    "total_embedding": 1,
    "pruned_pct_layer_level": 0.0,
    "active_layer_level": 32,
    "total_layer_level": 32,
    "pruned_pct_attention_blocks": 78.125,
    "active_attention_blocks": 7,
    "total_attention_blocks": 32,
    "pruned_pct_mlp_blocks": 43.75,
    "active_mlp_blocks": 18,
    "total_mlp_blocks": 32,
    "pruned_pct_attention_heads": 96.484375,
    "active_attention_heads": 36,
    "total_attention_heads": 1024,
    "pruned_pct_attention_neurons": 97.052001953125,
    "active_attention_neurons": 3864,
    "total_attention_neurons": 131072,
    "pruned_pct_mlp_hidden": 87.70337785993304,
    "active_mlp_hidden": 56411,
    "total_mlp_hidden": 458752,
    "pruned_pct_mlp_output": 76.81427001953125,
    "active_mlp_output": 30390,
    "total_mlp_output": 131072,
    "sparsity_attention_blocks": 7.041017532348633,
    "sparsity_mlp_blocks": 17.992088317871094,
    "sparsity_attention_heads": 1.3150116205215454,
    "sparsity_attention_neurons": 1.2095513343811035,
    "sparsity_mlp_hidden": 4.407508850097656,
    "sparsity_mlp_output": 7.689605712890625,
    "sparsity_total_sparsity": 39.654788970947266
  },
  {
    "model": "meta-llama/Llama-3.1-8B",
    "model_short": "Llama-3.1-8B",
    "task": "ioi",
    "lambda_sparsity": 0.83,
    "seed": 42,
    "num_epochs": 500,
    "learning_rate": 0.01,
    "batch_size": 32,
    "training_time_seconds": 1138.2633678913116,
    "baseline_accuracy": 1.0,
    "baseline_logit_diff": 5.808390625,
    "final_accuracy": 0.223,
    "final_logit_diff": -2.5284375,
    "final_kl_div": 1.523927490234375,
    "final_exact_match": 0.272,
    "accuracy_drop": 0.777,
    "final_train_loss": 30.15005602155413,
    "final_train_kl": 0.5846570900508335,
    "final_train_sparsity": 35.71808842250279,
    "final_train_task_loss": 2.3803013392857144,
    "compression_ratio": 18.03878888064963,
    "reduction_percentage": 94.4563905780132,
    "active_prunable_params": 386906344,
    "total_prunable_params": 6979321856,
    "effective_compression": 5.582624384203477,
    "pruned_pct_embedding": 100.0,
    "active_embedding": 0,
    "total_embedding": 1,
    "pruned_pct_layer_level": 0.0,
    "active_layer_level": 32,
    "total_layer_level": 32,
    "pruned_pct_attention_blocks": 84.375,
    "active_attention_blocks": 5,
    "total_attention_blocks": 32,
    "pruned_pct_mlp_blocks": 46.875,
    "active_mlp_blocks": 17,
    "total_mlp_blocks": 32,
    "pruned_pct_attention_heads": 97.265625,
    "active_attention_heads": 28,
    "total_attention_heads": 1024,
    "pruned_pct_attention_neurons": 97.49526977539062,
    "active_attention_neurons": 3283,
    "total_attention_neurons": 131072,
    "pruned_pct_mlp_hidden": 87.87209647042411,
    "active_mlp_hidden": 55637,
    "total_mlp_hidden": 458752,
    "pruned_pct_mlp_output": 77.97088623046875,
    "active_mlp_output": 28874,
    "total_mlp_output": 131072,
    "sparsity_attention_blocks": 5.044289588928223,
    "sparsity_mlp_blocks": 16.992366790771484,
    "sparsity_attention_heads": 1.0586459636688232,
    "sparsity_attention_neurons": 1.0224461555480957,
    "sparsity_mlp_hidden": 4.291458606719971,
    "sparsity_mlp_output": 7.301414966583252,
    "sparsity_total_sparsity": 35.71062469482422
  },
  {
    "model": "meta-llama/Llama-3.1-8B",
    "model_short": "Llama-3.1-8B",
    "task": "ioi",
    "lambda_sparsity": 0.85,
    "seed": 42,
    "num_epochs": 500,
    "learning_rate": 0.01,
    "batch_size": 32,
    "training_time_seconds": 1136.8140816688538,
    "baseline_accuracy": 1.0,
    "baseline_logit_diff": 5.808390625,
    "final_accuracy": 0.13,
    "final_logit_diff": -3.6136875,
    "final_kl_div": 1.757550537109375,
    "final_exact_match": 0.256,
    "accuracy_drop": 0.87,
    "final_train_loss": 29.491378784179688,
    "final_train_kl": 0.6787943499428886,
    "final_train_sparsity": 33.9944703238351,
    "final_train_task_loss": 3.2950613839285716,
    "compression_ratio": 19.208670947403732,
    "reduction_percentage": 94.79401774991018,
    "active_prunable_params": 363342257,
    "total_prunable_params": 6979321856,
    "effective_compression": 5.675591952349426,
    "pruned_pct_embedding": 100.0,
    "active_embedding": 0,
    "total_embedding": 1,
    "pruned_pct_layer_level": 0.0,
    "active_layer_level": 32,
    "total_layer_level": 32,
    "pruned_pct_attention_blocks": 84.375,
    "active_attention_blocks": 5,
    "total_attention_blocks": 32,
    "pruned_pct_mlp_blocks": 50.0,
    "active_mlp_blocks": 16,
    "total_mlp_blocks": 32,
    "pruned_pct_attention_heads": 97.265625,
    "active_attention_heads": 28,
    "total_attention_heads": 1024,
    "pruned_pct_attention_neurons": 97.52731323242188,
    "active_attention_neurons": 3241,
    "total_attention_neurons": 131072,
    "pruned_pct_mlp_hidden": 88.63961356026786,
    "active_mlp_hidden": 52116,
    "total_mlp_hidden": 458752,
    "pruned_pct_mlp_output": 79.31747436523438,
    "active_mlp_output": 27109,
    "total_mlp_output": 131072,
    "sparsity_attention_blocks": 5.039944171905518,
    "sparsity_mlp_blocks": 16.014745712280273,
    "sparsity_attention_heads": 1.0437239408493042,
    "sparsity_attention_neurons": 0.9644851684570312,
    "sparsity_mlp_hidden": 4.009270191192627,
    "sparsity_mlp_output": 6.914714336395264,
    "sparsity_total_sparsity": 33.98686981201172
  },
  {
    "model": "meta-llama/Llama-3.1-8B",
    "model_short": "Llama-3.1-8B",
    "task": "ioi",
    "lambda_sparsity": 0.88,
    "seed": 42,
    "num_epochs": 500,
    "learning_rate": 0.01,
    "batch_size": 32,
    "training_time_seconds": 1134.597076177597,
    "baseline_accuracy": 1.0,
    "baseline_logit_diff": 5.808390625,
    "final_accuracy": 0.018,
    "final_logit_diff": -5.897984375,
    "final_kl_div": 2.32918115234375,
    "final_exact_match": 0.224,
    "accuracy_drop": 0.982,
    "final_train_loss": 27.18479401724679,
    "final_train_kl": 1.3142401490892683,
    "final_train_sparsity": 29.752001898629324,
    "final_train_task_loss": 7.044363839285714,
    "compression_ratio": 23.80581095320784,
    "reduction_percentage": 95.79934494999739,
    "active_prunable_params": 293177236,
    "total_prunable_params": 6979321856,
    "effective_compression": 5.971707802214709,
    "pruned_pct_embedding": 100.0,
    "active_embedding": 0,
    "total_embedding": 1,
    "pruned_pct_layer_level": 0.0,
    "active_layer_level": 32,
    "total_layer_level": 32,
    "pruned_pct_attention_blocks": 87.5,
    "active_attention_blocks": 4,
    "total_attention_blocks": 32,
    "pruned_pct_mlp_blocks": 53.125,
    "active_mlp_blocks": 15,
    "total_mlp_blocks": 32,
    "pruned_pct_attention_heads": 98.14453125,
    "active_attention_heads": 19,
    "total_attention_heads": 1024,
    "pruned_pct_attention_neurons": 98.28414916992188,
    "active_attention_neurons": 2249,
    "total_attention_neurons": 131072,
    "pruned_pct_mlp_hidden": 90.39677211216518,
    "active_mlp_hidden": 44055,
    "total_mlp_hidden": 458752,
    "pruned_pct_mlp_output": 82.00149536132812,
    "active_mlp_output": 23591,
    "total_mlp_output": 131072,
    "sparsity_attention_blocks": 4.038934707641602,
    "sparsity_mlp_blocks": 15.010964393615723,
    "sparsity_attention_heads": 0.6796201467514038,
    "sparsity_attention_neurons": 0.690541684627533,
    "sparsity_mlp_hidden": 3.3545939922332764,
    "sparsity_mlp_output": 5.971940040588379,
    "sparsity_total_sparsity": 29.746597290039062
  },
  {
    "model": "meta-llama/Llama-3.1-8B",
    "model_short": "Llama-3.1-8B",
    "task": "ioi",
    "lambda_sparsity": 0.9,
    "seed": 42,
    "num_epochs": 500,
    "learning_rate": 0.01,
    "batch_size": 32,
    "training_time_seconds": 1133.6565606594086,
    "baseline_accuracy": 1.0,
    "baseline_logit_diff": 5.808390625,
    "final_accuracy": 0.0,
    "final_logit_diff": -8.899234375,
    "final_kl_div": 3.08347607421875,
    "final_exact_match": 0.178,
    "accuracy_drop": 1.0,
    "final_train_loss": 5.74417393548148,
    "final_train_kl": 2.5781942435673306,
    "final_train_sparsity": 4.696830068315778,
    "final_train_task_loss": 12.592075892857142,
    "compression_ratio": 419.7423058661078,
    "reduction_percentage": 99.7617585871082,
    "active_prunable_params": 16627635,
    "total_prunable_params": 6979321856,
    "effective_compression": 7.517612883130181,
    "pruned_pct_embedding": 100.0,
    "active_embedding": 0,
    "total_embedding": 1,
    "pruned_pct_layer_level": 0.0,
    "active_layer_level": 32,
    "total_layer_level": 32,
    "pruned_pct_attention_blocks": 100.0,
    "active_attention_blocks": 0,
    "total_attention_blocks": 32,
    "pruned_pct_mlp_blocks": 96.875,
    "active_mlp_blocks": 1,
    "total_mlp_blocks": 32,
    "pruned_pct_attention_heads": 100.0,
    "active_attention_heads": 0,
    "total_attention_heads": 1024,
    "pruned_pct_attention_neurons": 100.0,
    "active_attention_neurons": 0,
    "total_attention_neurons": 131072,
    "pruned_pct_mlp_hidden": 99.23793247767857,
    "active_mlp_hidden": 3496,
    "total_mlp_hidden": 458752,
    "pruned_pct_mlp_output": 99.49722290039062,
    "active_mlp_output": 659,
    "total_mlp_output": 131072,
    "sparsity_attention_blocks": 0.12968634068965912,
    "sparsity_mlp_blocks": 1.0927587747573853,
    "sparsity_attention_heads": 0.4675096273422241,
    "sparsity_attention_neurons": 0.5007402300834656,
    "sparsity_mlp_hidden": 1.1491055488586426,
    "sparsity_mlp_output": 1.3381496667861938,
    "sparsity_total_sparsity": 4.677949905395508
  },
  {
    "model": "meta-llama/Llama-3.1-8B",
    "model_short": "Llama-3.1-8B",
    "task": "ioi",
    "lambda_sparsity": 0.93,
    "seed": 42,
    "num_epochs": 500,
    "learning_rate": 0.01,
    "batch_size": 32,
    "training_time_seconds": 1132.6114797592163,
    "baseline_accuracy": 1.0,
    "baseline_logit_diff": 5.808390625,
    "final_accuracy": 0.0,
    "final_logit_diff": -8.899234375,
    "final_kl_div": 3.08347607421875,
    "final_exact_match": 0.178,
    "accuracy_drop": 1.0,
    "final_train_loss": 2.000997304916382,
    "final_train_kl": 2.5781942435673306,
    "final_train_sparsity": 1.0097616570336478,
    "final_train_task_loss": 12.592075892857142,
    "compression_ratio": Infinity,
    "reduction_percentage": 100.0,
    "active_prunable_params": 0,
    "total_prunable_params": 6979321856,
    "effective_compression": 7.6364725521687316,
    "pruned_pct_embedding": 100.0,
    "active_embedding": 0,
    "total_embedding": 1,
    "pruned_pct_layer_level": 0.0,
    "active_layer_level": 32,
    "total_layer_level": 32,
    "pruned_pct_attention_blocks": 100.0,
    "active_attention_blocks": 0,
    "total_attention_blocks": 32,
    "pruned_pct_mlp_blocks": 100.0,
    "active_mlp_blocks": 0,
    "total_mlp_blocks": 32,
    "pruned_pct_attention_heads": 100.0,
    "active_attention_heads": 0,
    "total_attention_heads": 1024,
    "pruned_pct_attention_neurons": 100.0,
    "active_attention_neurons": 0,
    "total_attention_neurons": 131072,
    "pruned_pct_mlp_hidden": 100.0,
    "active_mlp_hidden": 0,
    "total_mlp_hidden": 458752,
    "pruned_pct_mlp_output": 100.0,
    "active_mlp_output": 0,
    "total_mlp_output": 131072,
    "sparsity_attention_blocks": 0.05157938972115517,
    "sparsity_mlp_blocks": 0.0731486901640892,
    "sparsity_attention_heads": 0.13973084092140198,
    "sparsity_attention_neurons": 0.1520841121673584,
    "sparsity_mlp_hidden": 0.35279732942581177,
    "sparsity_mlp_output": 0.2372184693813324,
    "sparsity_total_sparsity": 1.0065592527389526
  },
  {
    "model": "meta-llama/Llama-3.1-8B",
    "model_short": "Llama-3.1-8B",
    "task": "ioi",
    "lambda_sparsity": 0.95,
    "seed": 42,
    "num_epochs": 500,
    "learning_rate": 0.01,
    "batch_size": 32,
    "training_time_seconds": 1132.6546792984009,
    "baseline_accuracy": 1.0,
    "baseline_logit_diff": 5.808390625,
    "final_accuracy": 0.0,
    "final_logit_diff": -8.899234375,
    "final_kl_div": 3.08347607421875,
    "final_exact_match": 0.178,
    "accuracy_drop": 1.0,
    "final_train_loss": 1.2387491634913854,
    "final_train_kl": 2.5781942435673306,
    "final_train_sparsity": 0.5055112412997654,
    "final_train_task_loss": 12.592075892857142,
    "compression_ratio": Infinity,
    "reduction_percentage": 100.0,
    "active_prunable_params": 0,
    "total_prunable_params": 6979321856,
    "effective_compression": 7.6364725521687316,
    "pruned_pct_embedding": 100.0,
    "active_embedding": 0,
    "total_embedding": 1,
    "pruned_pct_layer_level": 0.0,
    "active_layer_level": 32,
    "total_layer_level": 32,
    "pruned_pct_attention_blocks": 100.0,
    "active_attention_blocks": 0,
    "total_attention_blocks": 32,
    "pruned_pct_mlp_blocks": 100.0,
    "active_mlp_blocks": 0,
    "total_mlp_blocks": 32,
    "pruned_pct_attention_heads": 100.0,
    "active_attention_heads": 0,
    "total_attention_heads": 1024,
    "pruned_pct_attention_neurons": 100.0,
    "active_attention_neurons": 0,
    "total_attention_neurons": 131072,
    "pruned_pct_mlp_hidden": 100.0,
    "active_mlp_hidden": 0,
    "total_mlp_hidden": 458752,
    "pruned_pct_mlp_output": 100.0,
    "active_mlp_output": 0,
    "total_mlp_output": 131072,
    "sparsity_attention_blocks": 0.044496800750494,
    "sparsity_mlp_blocks": 0.058644071221351624,
    "sparsity_attention_heads": 0.04334566742181778,
    "sparsity_attention_neurons": 0.0680011659860611,
    "sparsity_mlp_hidden": 0.18859051167964935,
    "sparsity_mlp_output": 0.10085708647966385,
    "sparsity_total_sparsity": 0.5039352178573608
  },
  {
    "model": "meta-llama/Llama-3.1-8B",
    "model_short": "Llama-3.1-8B",
    "task": "gp",
    "lambda_sparsity": 0.7,
    "seed": 42,
    "num_epochs": 500,
    "learning_rate": 0.01,
    "batch_size": 32,
    "training_time_seconds": 840.9655909538269,
    "baseline_accuracy": 1.0,
    "baseline_logit_diff": 4.457342791411043,
    "final_accuracy": 0.9662576687116564,
    "final_logit_diff": 5.781345858895706,
    "final_kl_div": 0.6473391480241085,
    "final_exact_match": 0.8834355828220859,
    "accuracy_drop": 0.033742331288343586,
    "final_train_loss": 18.65581512451172,
    "final_train_kl": 0.9912757635116577,
    "final_train_sparsity": 26.173346328735352,
    "final_train_task_loss": 0.1236328125,
    "compression_ratio": 19.051865327316328,
    "reduction_percentage": 94.75117011998708,
    "active_prunable_params": 366332731,
    "total_prunable_params": 6979321856,
    "effective_compression": 5.6636224314012615,
    "pruned_pct_embedding": 100.0,
    "active_embedding": 0,
    "total_embedding": 1,
    "pruned_pct_layer_level": 0.0,
    "active_layer_level": 32,
    "total_layer_level": 32,
    "pruned_pct_attention_blocks": 81.25,
    "active_attention_blocks": 6,
    "total_attention_blocks": 32,
    "pruned_pct_mlp_blocks": 75.0,
    "active_mlp_blocks": 8,
    "total_mlp_blocks": 32,
    "pruned_pct_attention_heads": 97.4609375,
    "active_attention_heads": 26,
    "total_attention_heads": 1024,
    "pruned_pct_attention_neurons": 98.47946166992188,
    "active_attention_neurons": 1993,
    "total_attention_neurons": 131072,
    "pruned_pct_mlp_hidden": 88.71547154017857,
    "active_mlp_hidden": 51768,
    "total_mlp_hidden": 458752,
    "pruned_pct_mlp_output": 87.43820190429688,
    "active_mlp_output": 16465,
    "total_mlp_output": 131072,
    "sparsity_attention_blocks": 6.0410051345825195,
    "sparsity_mlp_blocks": 8.032735824584961,
    "sparsity_attention_heads": 1.0709707736968994,
    "sparsity_attention_neurons": 0.9393393993377686,
    "sparsity_mlp_hidden": 5.008855819702148,
    "sparsity_mlp_output": 5.058891773223877,
    "sparsity_total_sparsity": 26.15180206298828
  },
  {
    "model": "meta-llama/Llama-3.1-8B",
    "model_short": "Llama-3.1-8B",
    "task": "gp",
    "lambda_sparsity": 0.73,
    "seed": 42,
    "num_epochs": 500,
    "learning_rate": 0.01,
    "batch_size": 32,
    "training_time_seconds": 840.9197998046875,
    "baseline_accuracy": 1.0,
    "baseline_logit_diff": 4.457342791411043,
    "final_accuracy": 0.8865030674846626,
    "final_logit_diff": 3.947277607361963,
    "final_kl_div": 0.6393861361076495,
    "final_exact_match": 0.7944785276073619,
    "accuracy_drop": 0.11349693251533743,
    "final_train_loss": 17.380141067504884,
    "final_train_kl": 0.9610172033309936,
    "final_train_sparsity": 23.337799072265625,
    "final_train_task_loss": 0.3113813936710358,
    "compression_ratio": 21.492367837510237,
    "reduction_percentage": 95.3471855332072,
    "active_prunable_params": 324734897,
    "total_prunable_params": 6979321856,
    "effective_compression": 5.83479001617436,
    "pruned_pct_embedding": 100.0,
    "active_embedding": 0,
    "total_embedding": 1,
    "pruned_pct_layer_level": 0.0,
    "active_layer_level": 32,
    "total_layer_level": 32,
    "pruned_pct_attention_blocks": 84.375,
    "active_attention_blocks": 5,
    "total_attention_blocks": 32,
    "pruned_pct_mlp_blocks": 78.125,
    "active_mlp_blocks": 7,
    "total_mlp_blocks": 32,
    "pruned_pct_attention_heads": 97.75390625,
    "active_attention_heads": 23,
    "total_attention_heads": 1024,
    "pruned_pct_attention_neurons": 98.68392944335938,
    "active_attention_neurons": 1725,
    "total_attention_neurons": 131072,
    "pruned_pct_mlp_hidden": 89.837646484375,
    "active_mlp_hidden": 46620,
    "total_mlp_hidden": 458752,
    "pruned_pct_mlp_output": 88.81072998046875,
    "active_mlp_output": 14666,
    "total_mlp_output": 131072,
    "sparsity_attention_blocks": 5.160540580749512,
    "sparsity_mlp_blocks": 7.113096714019775,
    "sparsity_attention_heads": 1.0341076850891113,
    "sparsity_attention_neurons": 0.8573914170265198,
    "sparsity_mlp_hidden": 4.492922782897949,
    "sparsity_mlp_output": 4.659002780914307,
    "sparsity_total_sparsity": 23.317052841186523
  },
  {
    "model": "meta-llama/Llama-3.1-8B",
    "model_short": "Llama-3.1-8B",
    "task": "gp",
    "lambda_sparsity": 0.75,
    "seed": 42,
    "num_epochs": 500,
    "learning_rate": 0.01,
    "batch_size": 32,
    "training_time_seconds": 840.5555558204651,
    "baseline_accuracy": 1.0,
    "baseline_logit_diff": 4.457342791411043,
    "final_accuracy": 0.8987730061349694,
    "final_logit_diff": 3.9853335889570554,
    "final_kl_div": 0.6400240096577837,
    "final_exact_match": 0.7975460122699386,
    "accuracy_drop": 0.10122699386503065,
    "final_train_loss": 17.203647232055665,
    "final_train_kl": 1.0412188172340393,
    "final_train_sparsity": 22.508494186401368,
    "final_train_task_loss": 0.2478870742022991,
    "compression_ratio": 23.3063286784403,
    "reduction_percentage": 95.70931992851771,
    "active_prunable_params": 299460372,
    "total_prunable_params": 6979321856,
    "effective_compression": 5.943937505178845,
    "pruned_pct_embedding": 100.0,
    "active_embedding": 0,
    "total_embedding": 1,
    "pruned_pct_layer_level": 0.0,
    "active_layer_level": 32,
    "total_layer_level": 32,
    "pruned_pct_attention_blocks": 84.375,
    "active_attention_blocks": 5,
    "total_attention_blocks": 32,
    "pruned_pct_mlp_blocks": 78.125,
    "active_mlp_blocks": 7,
    "total_mlp_blocks": 32,
    "pruned_pct_attention_heads": 97.8515625,
    "active_attention_heads": 22,
    "total_attention_heads": 1024,
    "pruned_pct_attention_neurons": 98.71978759765625,
    "active_attention_neurons": 1678,
    "total_attention_neurons": 131072,
    "pruned_pct_mlp_hidden": 90.55219377790179,
    "active_mlp_hidden": 43342,
    "total_mlp_hidden": 458752,
    "pruned_pct_mlp_output": 89.21432495117188,
    "active_mlp_output": 14137,
    "total_mlp_output": 131072,
    "sparsity_attention_blocks": 5.068660736083984,
    "sparsity_mlp_blocks": 7.095301151275635,
    "sparsity_attention_heads": 1.0207573175430298,
    "sparsity_attention_neurons": 0.7933562397956848,
    "sparsity_mlp_hidden": 4.10134220123291,
    "sparsity_mlp_output": 4.412384033203125,
    "sparsity_total_sparsity": 22.491792678833008
  },
  {
    "model": "meta-llama/Llama-3.1-8B",
    "model_short": "Llama-3.1-8B",
    "task": "gp",
    "lambda_sparsity": 0.78,
    "seed": 42,
    "num_epochs": 500,
    "learning_rate": 0.01,
    "batch_size": 32,
    "training_time_seconds": 840.6070981025696,
    "baseline_accuracy": 1.0,
    "baseline_logit_diff": 4.457342791411043,
    "final_accuracy": 0.843558282208589,
    "final_logit_diff": 2.0359470858895707,
    "final_kl_div": 0.8087289260208972,
    "final_exact_match": 0.6840490797546013,
    "accuracy_drop": 0.15644171779141103,
    "final_train_loss": 16.203690338134766,
    "final_train_kl": 1.095170521736145,
    "final_train_sparsity": 20.195912551879882,
    "final_train_task_loss": 0.9542791247367859,
    "compression_ratio": 27.63520898720331,
    "reduction_percentage": 96.3814277631732,
    "active_prunable_params": 252551803,
    "total_prunable_params": 6979321856,
    "effective_compression": 6.157722802768887,
    "pruned_pct_embedding": 100.0,
    "active_embedding": 0,
    "total_embedding": 1,
    "pruned_pct_layer_level": 0.0,
    "active_layer_level": 32,
    "total_layer_level": 32,
    "pruned_pct_attention_blocks": 84.375,
    "active_attention_blocks": 5,
    "total_attention_blocks": 32,
    "pruned_pct_mlp_blocks": 81.25,
    "active_mlp_blocks": 6,
    "total_mlp_blocks": 32,
    "pruned_pct_attention_heads": 98.14453125,
    "active_attention_heads": 19,
    "total_attention_heads": 1024,
    "pruned_pct_attention_neurons": 98.89450073242188,
    "active_attention_neurons": 1449,
    "total_attention_neurons": 131072,
    "pruned_pct_mlp_hidden": 91.85812813895089,
    "active_mlp_hidden": 37351,
    "total_mlp_hidden": 458752,
    "pruned_pct_mlp_output": 90.81878662109375,
    "active_mlp_output": 12034,
    "total_mlp_output": 131072,
    "sparsity_attention_blocks": 5.055543899536133,
    "sparsity_mlp_blocks": 6.131916046142578,
    "sparsity_attention_heads": 0.8558511137962341,
    "sparsity_attention_neurons": 0.7029579281806946,
    "sparsity_mlp_hidden": 3.5060231685638428,
    "sparsity_mlp_output": 3.9274911880493164,
    "sparsity_total_sparsity": 20.179777145385742
  },
  {
    "model": "meta-llama/Llama-3.1-8B",
    "model_short": "Llama-3.1-8B",
    "task": "gp",
    "lambda_sparsity": 0.8,
    "seed": 42,
    "num_epochs": 500,
    "learning_rate": 0.01,
    "batch_size": 32,
    "training_time_seconds": 840.8104612827301,
    "baseline_accuracy": 1.0,
    "baseline_logit_diff": 4.457342791411043,
    "final_accuracy": 0.7699386503067485,
    "final_logit_diff": 2.259010736196319,
    "final_kl_div": 0.801887933461944,
    "final_exact_match": 0.6717791411042945,
    "accuracy_drop": 0.23006134969325154,
    "final_train_loss": 16.207050704956053,
    "final_train_kl": 1.0158246278762817,
    "final_train_sparsity": 19.733092498779296,
    "final_train_task_loss": 1.0870561122894287,
    "compression_ratio": 33.42638227904693,
    "reduction_percentage": 97.0083510933014,
    "active_prunable_params": 208796806,
    "total_prunable_params": 6979321856,
    "effective_compression": 6.371479313385107,
    "pruned_pct_embedding": 100.0,
    "active_embedding": 0,
    "total_embedding": 1,
    "pruned_pct_layer_level": 0.0,
    "active_layer_level": 32,
    "total_layer_level": 32,
    "pruned_pct_attention_blocks": 87.5,
    "active_attention_blocks": 4,
    "total_attention_blocks": 32,
    "pruned_pct_mlp_blocks": 78.125,
    "active_mlp_blocks": 7,
    "total_mlp_blocks": 32,
    "pruned_pct_attention_heads": 98.33984375,
    "active_attention_heads": 17,
    "total_attention_heads": 1024,
    "pruned_pct_attention_neurons": 99.02801513671875,
    "active_attention_neurons": 1274,
    "total_attention_neurons": 131072,
    "pruned_pct_mlp_hidden": 93.36264474051339,
    "active_mlp_hidden": 30449,
    "total_mlp_hidden": 458752,
    "pruned_pct_mlp_output": 90.61355590820312,
    "active_mlp_output": 12303,
    "total_mlp_output": 131072,
    "sparsity_attention_blocks": 4.083498001098633,
    "sparsity_mlp_blocks": 7.134566783905029,
    "sparsity_attention_heads": 0.8365979194641113,
    "sparsity_attention_neurons": 0.6492319703102112,
    "sparsity_mlp_hidden": 3.23632550239563,
    "sparsity_mlp_output": 3.777623414993286,
    "sparsity_total_sparsity": 19.717844009399414
  },
  {
    "model": "meta-llama/Llama-3.1-8B",
    "model_short": "Llama-3.1-8B",
    "task": "gp",
    "lambda_sparsity": 0.83,
    "seed": 42,
    "num_epochs": 500,
    "learning_rate": 0.01,
    "batch_size": 32,
    "training_time_seconds": 840.4640212059021,
    "baseline_accuracy": 1.0,
    "baseline_logit_diff": 4.457342791411043,
    "final_accuracy": 0.656441717791411,
    "final_logit_diff": 1.1964148773006136,
    "final_kl_div": 0.9727376926164686,
    "final_exact_match": 0.5644171779141104,
    "accuracy_drop": 0.34355828220858897,
    "final_train_loss": 14.951560783386231,
    "final_train_kl": 1.0302957773208619,
    "final_train_sparsity": 17.548775100708006,
    "final_train_task_loss": 1.2407492995262146,
    "compression_ratio": 36.34067296896339,
    "reduction_percentage": 97.2482622959293,
    "active_prunable_params": 192052631,
    "total_prunable_params": 6979321856,
    "effective_compression": 6.457258812555932,
    "pruned_pct_embedding": 100.0,
    "active_embedding": 0,
    "total_embedding": 1,
    "pruned_pct_layer_level": 0.0,
    "active_layer_level": 32,
    "total_layer_level": 32,
    "pruned_pct_attention_blocks": 87.5,
    "active_attention_blocks": 4,
    "total_attention_blocks": 32,
    "pruned_pct_mlp_blocks": 81.25,
    "active_mlp_blocks": 6,
    "total_mlp_blocks": 32,
    "pruned_pct_attention_heads": 98.33984375,
    "active_attention_heads": 17,
    "total_attention_heads": 1024,
    "pruned_pct_attention_neurons": 99.041748046875,
    "active_attention_neurons": 1256,
    "total_attention_neurons": 131072,
    "pruned_pct_mlp_hidden": 93.94335065569196,
    "active_mlp_hidden": 27785,
    "total_mlp_hidden": 458752,
    "pruned_pct_mlp_output": 91.4337158203125,
    "active_mlp_output": 11228,
    "total_mlp_output": 131072,
    "sparsity_attention_blocks": 4.085318088531494,
    "sparsity_mlp_blocks": 6.071392059326172,
    "sparsity_attention_heads": 0.7841656804084778,
    "sparsity_attention_neurons": 0.5766032338142395,
    "sparsity_mlp_hidden": 2.7026047706604004,
    "sparsity_mlp_output": 3.3177943229675293,
    "sparsity_total_sparsity": 17.537879943847656
  },
  {
    "model": "meta-llama/Llama-3.1-8B",
    "model_short": "Llama-3.1-8B",
    "task": "gp",
    "lambda_sparsity": 0.85,
    "seed": 42,
    "num_epochs": 500,
    "learning_rate": 0.01,
    "batch_size": 32,
    "training_time_seconds": 840.3583381175995,
    "baseline_accuracy": 1.0,
    "baseline_logit_diff": 4.457342791411043,
    "final_accuracy": 0.50920245398773,
    "final_logit_diff": 0.12279524539877301,
    "final_kl_div": 1.2458091689033743,
    "final_exact_match": 0.43558282208588955,
    "accuracy_drop": 0.49079754601227,
    "final_train_loss": 14.022263145446777,
    "final_train_kl": 1.1236605286598205,
    "final_train_sparsity": 15.906203079223634,
    "final_train_task_loss": 2.2229403495788573,
    "compression_ratio": 38.53308455473226,
    "reduction_percentage": 97.40482753572556,
    "active_prunable_params": 181125439,
    "total_prunable_params": 6979321856,
    "effective_compression": 6.514494748226197,
    "pruned_pct_embedding": 100.0,
    "active_embedding": 0,
    "total_embedding": 1,
    "pruned_pct_layer_level": 0.0,
    "active_layer_level": 32,
    "total_layer_level": 32,
    "pruned_pct_attention_blocks": 87.5,
    "active_attention_blocks": 4,
    "total_attention_blocks": 32,
    "pruned_pct_mlp_blocks": 84.375,
    "active_mlp_blocks": 5,
    "total_mlp_blocks": 32,
    "pruned_pct_attention_heads": 98.33984375,
    "active_attention_heads": 17,
    "total_attention_heads": 1024,
    "pruned_pct_attention_neurons": 99.0509033203125,
    "active_attention_neurons": 1244,
    "total_attention_neurons": 131072,
    "pruned_pct_mlp_hidden": 94.31544712611607,
    "active_mlp_hidden": 26078,
    "total_mlp_hidden": 458752,
    "pruned_pct_mlp_output": 92.28744506835938,
    "active_mlp_output": 10109,
    "total_mlp_output": 131072,
    "sparsity_attention_blocks": 4.062255859375,
    "sparsity_mlp_blocks": 5.086270332336426,
    "sparsity_attention_heads": 0.7596903443336487,
    "sparsity_attention_neurons": 0.5334169268608093,
    "sparsity_mlp_hidden": 2.4062979221343994,
    "sparsity_mlp_output": 3.0496203899383545,
    "sparsity_total_sparsity": 15.897546768188477
  },
  {
    "model": "meta-llama/Llama-3.1-8B",
    "model_short": "Llama-3.1-8B",
    "task": "gp",
    "lambda_sparsity": 0.88,
    "seed": 42,
    "num_epochs": 500,
    "learning_rate": 0.01,
    "batch_size": 32,
    "training_time_seconds": 840.416095495224,
    "baseline_accuracy": 1.0,
    "baseline_logit_diff": 4.457342791411043,
    "final_accuracy": 0.4938650306748466,
    "final_logit_diff": 0.027128067484662576,
    "final_kl_div": 1.2866546069186158,
    "final_exact_match": 0.4171779141104294,
    "accuracy_drop": 0.5061349693251533,
    "final_train_loss": 13.603035736083985,
    "final_train_kl": 1.1327300786972045,
    "final_train_sparsity": 15.002137184143066,
    "final_train_task_loss": 2.2102272748947143,
    "compression_ratio": 43.166516035110924,
    "reduction_percentage": 97.68338959950668,
    "active_prunable_params": 161683696,
    "total_prunable_params": 6979321856,
    "effective_compression": 6.6188781883477255,
    "pruned_pct_embedding": 100.0,
    "active_embedding": 0,
    "total_embedding": 1,
    "pruned_pct_layer_level": 0.0,
    "active_layer_level": 32,
    "total_layer_level": 32,
    "pruned_pct_attention_blocks": 87.5,
    "active_attention_blocks": 4,
    "total_attention_blocks": 32,
    "pruned_pct_mlp_blocks": 84.375,
    "active_mlp_blocks": 5,
    "total_mlp_blocks": 32,
    "pruned_pct_attention_heads": 98.4375,
    "active_attention_heads": 16,
    "total_attention_heads": 1024,
    "pruned_pct_attention_neurons": 99.078369140625,
    "active_attention_neurons": 1208,
    "total_attention_neurons": 131072,
    "pruned_pct_mlp_hidden": 94.90988595145089,
    "active_mlp_hidden": 23351,
    "total_mlp_hidden": 458752,
    "pruned_pct_mlp_output": 92.6177978515625,
    "active_mlp_output": 9676,
    "total_mlp_output": 131072,
    "sparsity_attention_blocks": 4.054817199707031,
    "sparsity_mlp_blocks": 5.06863260269165,
    "sparsity_attention_heads": 0.6914705038070679,
    "sparsity_attention_neurons": 0.4945530891418457,
    "sparsity_mlp_hidden": 2.0235278606414795,
    "sparsity_mlp_output": 2.663069725036621,
    "sparsity_total_sparsity": 14.99606704711914
  },
  {
    "model": "meta-llama/Llama-3.1-8B",
    "model_short": "Llama-3.1-8B",
    "task": "gp",
    "lambda_sparsity": 0.9,
    "seed": 42,
    "num_epochs": 500,
    "learning_rate": 0.01,
    "batch_size": 32,
    "training_time_seconds": 839.8700313568115,
    "baseline_accuracy": 1.0,
    "baseline_logit_diff": 4.457342791411043,
    "final_accuracy": 0.0736196319018405,
    "final_logit_diff": -3.6433090490797544,
    "final_kl_div": 3.0358193988449003,
    "final_exact_match": 0.06134969325153374,
    "accuracy_drop": 0.9263803680981595,
    "final_train_loss": 6.50442419052124,
    "final_train_kl": 3.34771523475647,
    "final_train_sparsity": 6.008616352081299,
    "final_train_task_loss": 7.618980789184571,
    "compression_ratio": 385.050695139206,
    "reduction_percentage": 99.74029393723379,
    "active_prunable_params": 18125722,
    "total_prunable_params": 6979321856,
    "effective_compression": 7.507085519178696,
    "pruned_pct_embedding": 100.0,
    "active_embedding": 0,
    "total_embedding": 1,
    "pruned_pct_layer_level": 0.0,
    "active_layer_level": 32,
    "total_layer_level": 32,
    "pruned_pct_attention_blocks": 96.875,
    "active_attention_blocks": 1,
    "total_attention_blocks": 32,
    "pruned_pct_mlp_blocks": 96.875,
    "active_mlp_blocks": 1,
    "total_mlp_blocks": 32,
    "pruned_pct_attention_heads": 99.609375,
    "active_attention_heads": 4,
    "total_attention_heads": 1024,
    "pruned_pct_attention_neurons": 99.77645874023438,
    "active_attention_neurons": 293,
    "total_attention_neurons": 131072,
    "pruned_pct_mlp_hidden": 99.45569719587054,
    "active_mlp_hidden": 2497,
    "total_mlp_hidden": 458752,
    "pruned_pct_mlp_output": 99.05624389648438,
    "active_mlp_output": 1237,
    "total_mlp_output": 131072,
    "sparsity_attention_blocks": 1.0338143110275269,
    "sparsity_mlp_blocks": 1.7964478731155396,
    "sparsity_attention_heads": 0.540424108505249,
    "sparsity_attention_neurons": 0.398673415184021,
    "sparsity_mlp_hidden": 0.8939679861068726,
    "sparsity_mlp_output": 1.2992573976516724,
    "sparsity_total_sparsity": 5.962583065032959
  },
  {
    "model": "meta-llama/Llama-3.1-8B",
    "model_short": "Llama-3.1-8B",
    "task": "gp",
    "lambda_sparsity": 0.93,
    "seed": 42,
    "num_epochs": 500,
    "learning_rate": 0.01,
    "batch_size": 32,
    "training_time_seconds": 840.0940012931824,
    "baseline_accuracy": 1.0,
    "baseline_logit_diff": 4.457342791411043,
    "final_accuracy": 0.07668711656441718,
    "final_logit_diff": -3.6439800613496933,
    "final_kl_div": 3.036936754097968,
    "final_exact_match": 0.06134969325153374,
    "accuracy_drop": 0.9233128834355828,
    "final_train_loss": 1.8591754913330079,
    "final_train_kl": 3.350047254562378,
    "final_train_sparsity": 1.1734421968460083,
    "final_train_task_loss": 7.619584655761718,
    "compression_ratio": Infinity,
    "reduction_percentage": 100.0,
    "active_prunable_params": 0,
    "total_prunable_params": 6979321856,
    "effective_compression": 7.6364725521687316,
    "pruned_pct_embedding": 100.0,
    "active_embedding": 0,
    "total_embedding": 1,
    "pruned_pct_layer_level": 0.0,
    "active_layer_level": 32,
    "total_layer_level": 32,
    "pruned_pct_attention_blocks": 100.0,
    "active_attention_blocks": 0,
    "total_attention_blocks": 32,
    "pruned_pct_mlp_blocks": 100.0,
    "active_mlp_blocks": 0,
    "total_mlp_blocks": 32,
    "pruned_pct_attention_heads": 100.0,
    "active_attention_heads": 0,
    "total_attention_heads": 1024,
    "pruned_pct_attention_neurons": 100.0,
    "active_attention_neurons": 0,
    "total_attention_neurons": 131072,
    "pruned_pct_mlp_hidden": 100.0,
    "active_mlp_hidden": 0,
    "total_mlp_hidden": 458752,
    "pruned_pct_mlp_output": 100.0,
    "active_mlp_output": 0,
    "total_mlp_output": 131072,
    "sparsity_attention_blocks": 0.07666508853435516,
    "sparsity_mlp_blocks": 0.08995742350816727,
    "sparsity_attention_heads": 0.3227311074733734,
    "sparsity_attention_neurons": 0.22724032402038574,
    "sparsity_mlp_hidden": 0.2587137222290039,
    "sparsity_mlp_output": 0.1949985921382904,
    "sparsity_total_sparsity": 1.1703064441680908
  },
  {
    "model": "meta-llama/Llama-3.1-8B",
    "model_short": "Llama-3.1-8B",
    "task": "gp",
    "lambda_sparsity": 0.95,
    "seed": 42,
    "num_epochs": 500,
    "learning_rate": 0.01,
    "batch_size": 32,
    "training_time_seconds": 839.4517195224762,
    "baseline_accuracy": 1.0,
    "baseline_logit_diff": 4.457342791411043,
    "final_accuracy": 0.07668711656441718,
    "final_logit_diff": -3.6439800613496933,
    "final_kl_div": 3.036936754097968,
    "final_exact_match": 0.06134969325153374,
    "accuracy_drop": 0.9233128834355828,
    "final_train_loss": 1.2460808038711548,
    "final_train_kl": 3.350047254562378,
    "final_train_sparsity": 0.7343149662017823,
    "final_train_task_loss": 7.619584655761718,
    "compression_ratio": Infinity,
    "reduction_percentage": 100.0,
    "active_prunable_params": 0,
    "total_prunable_params": 6979321856,
    "effective_compression": 7.6364725521687316,
    "pruned_pct_embedding": 100.0,
    "active_embedding": 0,
    "total_embedding": 1,
    "pruned_pct_layer_level": 0.0,
    "active_layer_level": 32,
    "total_layer_level": 32,
    "pruned_pct_attention_blocks": 100.0,
    "active_attention_blocks": 0,
    "total_attention_blocks": 32,
    "pruned_pct_mlp_blocks": 100.0,
    "active_mlp_blocks": 0,
    "total_mlp_blocks": 32,
    "pruned_pct_attention_heads": 100.0,
    "active_attention_heads": 0,
    "total_attention_heads": 1024,
    "pruned_pct_attention_neurons": 100.0,
    "active_attention_neurons": 0,
    "total_attention_neurons": 131072,
    "pruned_pct_mlp_hidden": 100.0,
    "active_mlp_hidden": 0,
    "total_mlp_hidden": 458752,
    "pruned_pct_mlp_output": 100.0,
    "active_mlp_output": 0,
    "total_mlp_output": 131072,
    "sparsity_attention_blocks": 0.06755281984806061,
    "sparsity_mlp_blocks": 0.07695820927619934,
    "sparsity_attention_heads": 0.12956872582435608,
    "sparsity_attention_neurons": 0.15381182730197906,
    "sparsity_mlp_hidden": 0.17784756422042847,
    "sparsity_mlp_output": 0.12680752575397491,
    "sparsity_total_sparsity": 0.7325466275215149
  }
]